rtl/pwm_generator.vhdl
library ieee;
use ieee.std_logic_1164.all;
use ieee.numeric_std.all;

entity pwm_generator is
    generic (
        COUNTER_WIDTH : integer := 8  -- 8 bits = 0 to 255
    );
    port (
        clk        : in  std_logic;
        reset      : in  std_logic;
        enable     : in  std_logic;
        duty_cycle : in  std_logic_vector(COUNTER_WIDTH-1 downto 0);
        pwm_out    : out std_logic
    );
end entity pwm_generator;

architecture rtl of pwm_generator is
    signal counter : unsigned(COUNTER_WIDTH-1 downto 0);
    signal duty_unsigned : unsigned(COUNTER_WIDTH-1 downto 0);
begin
    -- Convert duty_cycle input to unsigned for comparison
    duty_unsigned <= unsigned(duty_cycle);
    
    -- PWM counter process
    process(clk, reset)
    begin
        if reset = '1' then
            counter <= (others => '0');
            pwm_out <= '0';
        elsif rising_edge(clk) then
            if enable = '1' then
                -- Increment counter (wraps automatically)
                counter <= counter + 1;
                
                -- Compare and generate PWM output
                if counter < duty_unsigned then
                    pwm_out <= '1';
                else
                    pwm_out <= '0';
                end if;
            else
                -- When disabled, keep counter at 0 and output low
                counter <= (others => '0');
                pwm_out <= '0';
            end if;
        end if;
    end process;
    
end architecture rtl;

rtl/interlock.vhdl
library ieee;
use ieee.std_logic_1164.all;
use ieee.numeric_std.all;

entity interlock is
    generic (
        SENSOR_WIDTH : integer := 12  -- 12-bit ADC values (0-4095)
    );
    port (
        clk                : in  std_logic;
        reset              : in  std_logic;
        
        -- Sensor inputs (from ADCs measuring current, voltage, temp)
        current_value      : in  std_logic_vector(SENSOR_WIDTH-1 downto 0);
        voltage_value      : in  std_logic_vector(SENSOR_WIDTH-1 downto 0);
        temperature_value  : in  std_logic_vector(SENSOR_WIDTH-1 downto 0);
        
        -- Threshold settings
        current_threshold  : in  std_logic_vector(SENSOR_WIDTH-1 downto 0);
        voltage_threshold  : in  std_logic_vector(SENSOR_WIDTH-1 downto 0);
        temp_threshold     : in  std_logic_vector(SENSOR_WIDTH-1 downto 0);
        
        -- Hysteresis (threshold - hysteresis = clear level)
        hysteresis         : in  std_logic_vector(SENSOR_WIDTH-1 downto 0);
        
        -- Outputs
        interlock_active   : out std_logic;  -- '1' = fault detected, disable PWM
        fault_current      : out std_logic;  -- Which fault occurred
        fault_voltage      : out std_logic;
        fault_temperature  : out std_logic
    );
end entity interlock;

architecture rtl of interlock is
    -- Convert to unsigned for comparison
    signal current_u      : unsigned(SENSOR_WIDTH-1 downto 0);
    signal voltage_u      : unsigned(SENSOR_WIDTH-1 downto 0);
    signal temperature_u  : unsigned(SENSOR_WIDTH-1 downto 0);
    
    signal current_thresh_u  : unsigned(SENSOR_WIDTH-1 downto 0);
    signal voltage_thresh_u  : unsigned(SENSOR_WIDTH-1 downto 0);
    signal temp_thresh_u     : unsigned(SENSOR_WIDTH-1 downto 0);
    signal hysteresis_u      : unsigned(SENSOR_WIDTH-1 downto 0);
    
    -- Fault flags (internal)
    signal fault_current_int      : std_logic;
    signal fault_voltage_int      : std_logic;
    signal fault_temperature_int  : std_logic;
    
begin
    -- Type conversions
    current_u       <= unsigned(current_value);
    voltage_u       <= unsigned(voltage_value);
    temperature_u   <= unsigned(temperature_value);
    
    current_thresh_u  <= unsigned(current_threshold);
    voltage_thresh_u  <= unsigned(voltage_threshold);
    temp_thresh_u     <= unsigned(temp_threshold);
    hysteresis_u      <= unsigned(hysteresis);
    
    -- Main interlock logic with hysteresis
    process(clk, reset)
        variable clear_current_thresh  : unsigned(SENSOR_WIDTH-1 downto 0);
        variable clear_voltage_thresh  : unsigned(SENSOR_WIDTH-1 downto 0);
        variable clear_temp_thresh     : unsigned(SENSOR_WIDTH-1 downto 0);
    begin
        if reset = '1' then
            fault_current_int     <= '0';
            fault_voltage_int     <= '0';
            fault_temperature_int <= '0';
            
        elsif rising_edge(clk) then
            -- Calculate clear thresholds (trip - hysteresis)
            clear_current_thresh := current_thresh_u - hysteresis_u;
            clear_voltage_thresh := voltage_thresh_u - hysteresis_u;
            clear_temp_thresh    := temp_thresh_u - hysteresis_u;
            
            -- Current interlock with hysteresis
            if current_u >= current_thresh_u then
                fault_current_int <= '1';  -- Trip
            elsif current_u < clear_current_thresh then
                fault_current_int <= '0';  -- Clear
            end if;
            -- Otherwise maintain current state (hysteresis region)
            
            -- Voltage interlock with hysteresis
            if voltage_u >= voltage_thresh_u then
                fault_voltage_int <= '1';
            elsif voltage_u < clear_voltage_thresh then
                fault_voltage_int <= '0';
            end if;
            
            -- Temperature interlock with hysteresis
            if temperature_u >= temp_thresh_u then
                fault_temperature_int <= '1';
            elsif temperature_u < clear_temp_thresh then
                fault_temperature_int <= '0';
            end if;
        end if;
    end process;
    
    -- Output assignment (combinational for fastest response)
    interlock_active  <= fault_current_int or fault_voltage_int or fault_temperature_int;
    fault_current     <= fault_current_int;
    fault_voltage     <= fault_voltage_int;
    fault_temperature <= fault_temperature_int;
    
end architecture rtl;

rtl/power_controller_fsm.vhdl
library ieee;
use ieee.std_logic_1164.all;
use ieee.numeric_std.all;

entity power_controller_fsm is
    port (
        clk              : in  std_logic;
        reset            : in  std_logic;
        
        -- Control inputs
        start_cmd        : in  std_logic;  -- User command to start
        stop_cmd         : in  std_logic;  -- User command to stop
        fault_ack        : in  std_logic;  -- Acknowledge fault to allow restart
        
        -- Status inputs
        interlock_active : in  std_logic;  -- From interlock system
        
        -- Outputs
        pwm_enable       : out std_logic;  -- Enable PWM generator
        state_idle       : out std_logic;  -- State indicators
        state_startup    : out std_logic;
        state_running    : out std_logic;
        state_fault      : out std_logic;
        state_shutdown   : out std_logic
    );
end entity power_controller_fsm;

architecture rtl of power_controller_fsm is
    -- State type definition
    type state_type is (IDLE, STARTUP, RUNNING, FAULT, SHUTDOWN);
    signal current_state : state_type;
    signal next_state    : state_type;
    
    -- Startup delay counter (simulates pre-charge time)
    signal startup_counter : unsigned(7 downto 0);
    constant STARTUP_DELAY : unsigned(7 downto 0) := to_unsigned(50, 8);  -- 50 clock cycles
    
    -- Shutdown delay counter
    signal shutdown_counter : unsigned(7 downto 0);
    constant SHUTDOWN_DELAY : unsigned(7 downto 0) := to_unsigned(30, 8);  -- 30 clock cycles
    
begin
    -- State register (sequential logic)
    process(clk, reset)
    begin
        if reset = '1' then
            current_state <= IDLE;
        elsif rising_edge(clk) then
            current_state <= next_state;
        end if;
    end process;
    
    -- Next state logic (combinational)
    process(current_state, start_cmd, stop_cmd, fault_ack, interlock_active, 
            startup_counter, shutdown_counter)
    begin
        -- Default: stay in current state
        next_state <= current_state;
        
        case current_state is
            when IDLE =>
                if start_cmd = '1' and interlock_active = '0' then
                    next_state <= STARTUP;
                end if;
            
            when STARTUP =>
                -- Check for faults during startup
                if interlock_active = '1' then
                    next_state <= FAULT;
                -- Wait for startup delay to complete
                elsif startup_counter >= STARTUP_DELAY then
                    next_state <= RUNNING;
                end if;
            
            when RUNNING =>
                -- Priority 1: Fault detection
                if interlock_active = '1' then
                    next_state <= FAULT;
                -- Priority 2: Stop command
                elsif stop_cmd = '1' then
                    next_state <= SHUTDOWN;
                end if;
            
            when FAULT =>
                -- Must acknowledge fault AND fault must be cleared to restart
                if fault_ack = '1' and interlock_active = '0' then
                    next_state <= IDLE;
                end if;
            
            when SHUTDOWN =>
                -- Wait for shutdown delay, then return to idle
                if shutdown_counter >= SHUTDOWN_DELAY then
                    next_state <= IDLE;
                end if;
        end case;
    end process;
    
    -- Output logic and counters (sequential)
    process(clk, reset)
    begin
        if reset = '1' then
            pwm_enable       <= '0';
            startup_counter  <= (others => '0');
            shutdown_counter <= (others => '0');
            
        elsif rising_edge(clk) then
            -- Default outputs
            pwm_enable <= '0';
            
            case current_state is
                when IDLE =>
                    startup_counter  <= (others => '0');
                    shutdown_counter <= (others => '0');
                
                when STARTUP =>
                    -- Increment startup counter
                    if startup_counter < STARTUP_DELAY then
                        startup_counter <= startup_counter + 1;
                    end if;
                    -- PWM disabled during startup
                    pwm_enable <= '0';
                
                when RUNNING =>
                    -- Enable PWM in running state
                    pwm_enable <= '1';
                    startup_counter  <= (others => '0');
                    shutdown_counter <= (others => '0');
                
                when FAULT =>
                    -- Immediately disable PWM
                    pwm_enable <= '0';
                    startup_counter  <= (others => '0');
                    shutdown_counter <= (others => '0');
                
                when SHUTDOWN =>
                    -- Increment shutdown counter
                    if shutdown_counter < SHUTDOWN_DELAY then
                        shutdown_counter <= shutdown_counter + 1;
                    end if;
                    -- PWM disabled during shutdown
                    pwm_enable <= '0';
            end case;
        end if;
    end process;
    
    -- State indicator outputs (for monitoring/debugging)
    state_idle     <= '1' when current_state = IDLE     else '0';
    state_startup  <= '1' when current_state = STARTUP  else '0';
    state_running  <= '1' when current_state = RUNNING  else '0';
    state_fault    <= '1' when current_state = FAULT    else '0';
    state_shutdown <= '1' when current_state = SHUTDOWN else '0';
    
end architecture rtl;

rtl/complete_power_controller.vhdl
library ieee;
use ieee.std_logic_1164.all;
use ieee.numeric_std.all;

entity complete_power_controller is
    generic (
        PWM_WIDTH    : integer := 8;
        SENSOR_WIDTH : integer := 12
    );
    port (
        clk                : in  std_logic;
        reset              : in  std_logic;
        
        -- User commands
        start_cmd          : in  std_logic;
        stop_cmd           : in  std_logic;
        fault_ack          : in  std_logic;
        
        -- PWM configuration
        duty_cycle         : in  std_logic_vector(PWM_WIDTH-1 downto 0);
        
        -- Sensor inputs
        current_value      : in  std_logic_vector(SENSOR_WIDTH-1 downto 0);
        voltage_value      : in  std_logic_vector(SENSOR_WIDTH-1 downto 0);
        temperature_value  : in  std_logic_vector(SENSOR_WIDTH-1 downto 0);
        
        -- Safety configuration
        current_threshold  : in  std_logic_vector(SENSOR_WIDTH-1 downto 0);
        voltage_threshold  : in  std_logic_vector(SENSOR_WIDTH-1 downto 0);
        temp_threshold     : in  std_logic_vector(SENSOR_WIDTH-1 downto 0);
        hysteresis         : in  std_logic_vector(SENSOR_WIDTH-1 downto 0);
        
        -- Outputs
        pwm_out            : out std_logic;
        
        -- Status outputs
        state_idle         : out std_logic;
        state_startup      : out std_logic;
        state_running      : out std_logic;
        state_fault        : out std_logic;
        state_shutdown     : out std_logic;
        
        interlock_active   : out std_logic;
        fault_current      : out std_logic;
        fault_voltage      : out std_logic;
        fault_temperature  : out std_logic
    );
end entity complete_power_controller;

architecture rtl of complete_power_controller is
    -- Internal signals
    signal pwm_enable_fsm    : std_logic;  -- Enable from FSM
    signal pwm_enable_final  : std_logic;  -- Final enable (FSM AND not interlock)
    signal interlock_active_i : std_logic;
    signal pwm_raw           : std_logic;
    
begin
    -- Instantiate State Machine
    fsm: entity work.power_controller_fsm
        port map (
            clk              => clk,
            reset            => reset,
            start_cmd        => start_cmd,
            stop_cmd         => stop_cmd,
            fault_ack        => fault_ack,
            interlock_active => interlock_active_i,
            pwm_enable       => pwm_enable_fsm,
            state_idle       => state_idle,
            state_startup    => state_startup,
            state_running    => state_running,
            state_fault      => state_fault,
            state_shutdown   => state_shutdown
        );
    
    -- Instantiate Safety Interlock System
    interlock_sys: entity work.interlock
        generic map (
            SENSOR_WIDTH => SENSOR_WIDTH
        )
        port map (
            clk               => clk,
            reset             => reset,
            current_value     => current_value,
            voltage_value     => voltage_value,
            temperature_value => temperature_value,
            current_threshold => current_threshold,
            voltage_threshold => voltage_threshold,
            temp_threshold    => temp_threshold,
            hysteresis        => hysteresis,
            interlock_active  => interlock_active_i,
            fault_current     => fault_current,
            fault_voltage     => fault_voltage,
            fault_temperature => fault_temperature
        );
    
    -- Instantiate PWM Generator
    pwm_gen: entity work.pwm_generator
        generic map (
            COUNTER_WIDTH => PWM_WIDTH
        )
        port map (
            clk        => clk,
            reset      => reset,
            enable     => pwm_enable_final,
            duty_cycle => duty_cycle,
            pwm_out    => pwm_raw
        );
    
    -- Triple-redundant safety logic:
    -- 1. FSM must enable (state = RUNNING)
    -- 2. No interlock active
    -- 3. Final gate on output
    pwm_enable_final <= pwm_enable_fsm and (not interlock_active_i);
    pwm_out <= pwm_raw and (not interlock_active_i);
    
    -- Pass through interlock status
    interlock_active <= interlock_active_i;
    
end architecture rtl;

tb/complete_power_controller_tb.vhdl
library ieee;
use ieee.std_logic_1164.all;
use ieee.numeric_std.all;

entity complete_power_controller_tb is
end entity complete_power_controller_tb;

architecture sim of complete_power_controller_tb is
    constant CLK_PERIOD   : time := 10 ns;
    constant PWM_WIDTH    : integer := 8;
    constant SENSOR_WIDTH : integer := 12;
    
    signal clk                : std_logic := '0';
    signal reset              : std_logic := '0';
    signal start_cmd          : std_logic := '0';
    signal stop_cmd           : std_logic := '0';
    signal fault_ack          : std_logic := '0';
    signal duty_cycle         : std_logic_vector(PWM_WIDTH-1 downto 0);
    signal current_value      : std_logic_vector(SENSOR_WIDTH-1 downto 0);
    signal voltage_value      : std_logic_vector(SENSOR_WIDTH-1 downto 0);
    signal temperature_value  : std_logic_vector(SENSOR_WIDTH-1 downto 0);
    signal current_threshold  : std_logic_vector(SENSOR_WIDTH-1 downto 0);
    signal voltage_threshold  : std_logic_vector(SENSOR_WIDTH-1 downto 0);
    signal temp_threshold     : std_logic_vector(SENSOR_WIDTH-1 downto 0);
    signal hysteresis         : std_logic_vector(SENSOR_WIDTH-1 downto 0);
    signal pwm_out            : std_logic;
    signal state_idle         : std_logic;
    signal state_startup      : std_logic;
    signal state_running      : std_logic;
    signal state_fault        : std_logic;
    signal state_shutdown     : std_logic;
    signal interlock_active   : std_logic;
    signal fault_current      : std_logic;
    signal fault_voltage      : std_logic;
    signal fault_temperature  : std_logic;
    
    signal sim_done : boolean := false;
    
begin
    -- Instantiate complete system
    uut: entity work.complete_power_controller
        generic map (
            PWM_WIDTH    => PWM_WIDTH,
            SENSOR_WIDTH => SENSOR_WIDTH
        )
        port map (
            clk               => clk,
            reset             => reset,
            start_cmd         => start_cmd,
            stop_cmd          => stop_cmd,
            fault_ack         => fault_ack,
            duty_cycle        => duty_cycle,
            current_value     => current_value,
            voltage_value     => voltage_value,
            temperature_value => temperature_value,
            current_threshold => current_threshold,
            voltage_threshold => voltage_threshold,
            temp_threshold    => temp_threshold,
            hysteresis        => hysteresis,
            pwm_out           => pwm_out,
            state_idle        => state_idle,
            state_startup     => state_startup,
            state_running     => state_running,
            state_fault       => state_fault,
            state_shutdown    => state_shutdown,
            interlock_active  => interlock_active,
            fault_current     => fault_current,
            fault_voltage     => fault_voltage,
            fault_temperature => fault_temperature
        );
    
    -- Clock generation
    clk_gen: process
    begin
        while not sim_done loop
            clk <= '0';
            wait for CLK_PERIOD/2;
            clk <= '1';
            wait for CLK_PERIOD/2;
        end loop;
        wait;
    end process;
    
    -- Stimulus
    stim: process
    begin
        -- Initialize
        reset <= '1';
        duty_cycle        <= std_logic_vector(to_unsigned(128, PWM_WIDTH));
        current_value     <= std_logic_vector(to_unsigned(2000, SENSOR_WIDTH));
        voltage_value     <= std_logic_vector(to_unsigned(2500, SENSOR_WIDTH));
        temperature_value <= std_logic_vector(to_unsigned(2000, SENSOR_WIDTH));
        
        -- Configure thresholds
        current_threshold <= std_logic_vector(to_unsigned(3000, SENSOR_WIDTH));
        voltage_threshold <= std_logic_vector(to_unsigned(3500, SENSOR_WIDTH));
        temp_threshold    <= std_logic_vector(to_unsigned(2800, SENSOR_WIDTH));
        hysteresis        <= std_logic_vector(to_unsigned(200, SENSOR_WIDTH));
        
        wait for 50 ns;
        reset <= '0';
        wait for 50 ns;
        
        -- Test 1: Normal startup
        report "Test 1: Normal startup";
        start_cmd <= '1';
        wait for 20 ns;
        start_cmd <= '0';
        wait for 800 ns;
        
        -- Test 2: Adjust duty cycle
        report "Test 2: Change duty cycle to 25%";
        duty_cycle <= std_logic_vector(to_unsigned(64, PWM_WIDTH));
        wait for 1000 ns;
        
        -- Test 3: Emergency fault
        report "Test 3: Overcurrent fault";
        current_value <= std_logic_vector(to_unsigned(3300, SENSOR_WIDTH));
        wait for 500 ns;
        
        -- Test 4: Clear and acknowledge fault
        report "Test 4: Clear fault";
        current_value <= std_logic_vector(to_unsigned(2000, SENSOR_WIDTH));
        wait for 100 ns;
        fault_ack <= '1';
        wait for 20 ns;
        fault_ack <= '0';
        wait for 100 ns;
        
        -- Test 5: Restart
        report "Test 5: Restart after fault";
        start_cmd <= '1';
        wait for 20 ns;
        start_cmd <= '0';
        wait for 800 ns;
        
        -- Test 6: Normal shutdown
        report "Test 6: Normal shutdown";
        stop_cmd <= '1';
        wait for 20 ns;
        stop_cmd <= '0';
        wait for 500 ns;
        
        -- End
        report "Simulation complete";
        sim_done <= true;
        wait;
    end process;
    
end architecture sim;

sim/complete_system.vcd
$date
  Thu Jan 29 13:40:00 2026
$end
$version
  GHDL v0
$end
$timescale
  1 fs
$end
$scope module standard $end
$upscope $end
$scope module std_logic_1164 $end
$upscope $end
$scope module numeric_std $end
$upscope $end
$scope module complete_power_controller_tb $end
$var reg 1 ! clk $end
$var reg 1 " reset $end
$var reg 1 # start_cmd $end
$var reg 1 $ stop_cmd $end
$var reg 1 % fault_ack $end
$var reg 8 & duty_cycle[7:0] $end
$var reg 12 ' current_value[11:0] $end
$var reg 12 ( voltage_value[11:0] $end
$var reg 12 ) temperature_value[11:0] $end
$var reg 12 * current_threshold[11:0] $end
$var reg 12 + voltage_threshold[11:0] $end
$var reg 12 , temp_threshold[11:0] $end
$var reg 12 - hysteresis[11:0] $end
$var reg 1 . pwm_out $end
$var reg 1 / state_idle $end
$var reg 1 0 state_startup $end
$var reg 1 1 state_running $end
$var reg 1 2 state_fault $end
$var reg 1 3 state_shutdown $end
$var reg 1 4 interlock_active $end
$var reg 1 5 fault_current $end
$var reg 1 6 fault_voltage $end
$var reg 1 7 fault_temperature $end
$var reg 1 8 sim_done $end
$scope module uut $end
$var reg 1 9 clk $end
$var reg 1 : reset $end
$var reg 1 ; start_cmd $end
$var reg 1 < stop_cmd $end
$var reg 1 = fault_ack $end
$var reg 8 > duty_cycle[7:0] $end
$var reg 12 ? current_value[11:0] $end
$var reg 12 @ voltage_value[11:0] $end
$var reg 12 A temperature_value[11:0] $end
$var reg 12 B current_threshold[11:0] $end
$var reg 12 C voltage_threshold[11:0] $end
$var reg 12 D temp_threshold[11:0] $end
$var reg 12 E hysteresis[11:0] $end
$var reg 1 F pwm_out $end
$var reg 1 G state_idle $end
$var reg 1 H state_startup $end
$var reg 1 I state_running $end
$var reg 1 J state_fault $end
$var reg 1 K state_shutdown $end
$var reg 1 L interlock_active $end
$var reg 1 M fault_current $end
$var reg 1 N fault_voltage $end
$var reg 1 O fault_temperature $end
$var reg 1 P pwm_enable_fsm $end
$var reg 1 Q pwm_enable_final $end
$var reg 1 R interlock_active_i $end
$var reg 1 S pwm_raw $end
$scope module fsm $end
$var reg 1 T clk $end
$var reg 1 U reset $end
$var reg 1 V start_cmd $end
$var reg 1 W stop_cmd $end
$var reg 1 X fault_ack $end
$var reg 1 Y interlock_active $end
$var reg 1 Z pwm_enable $end
$var reg 1 [ state_idle $end
$var reg 1 \ state_startup $end
$var reg 1 ] state_running $end
$var reg 1 ^ state_fault $end
$var reg 1 _ state_shutdown $end
$comment current_state is not handled $end
$comment next_state is not handled $end
$var reg 8 ` startup_counter[7:0] $end
$var reg 8 a shutdown_counter[7:0] $end
$upscope $end
$scope module interlock_sys $end
$var reg 1 b clk $end
$var reg 1 c reset $end
$var reg 12 d current_value[11:0] $end
$var reg 12 e voltage_value[11:0] $end
$var reg 12 f temperature_value[11:0] $end
$var reg 12 g current_threshold[11:0] $end
$var reg 12 h voltage_threshold[11:0] $end
$var reg 12 i temp_threshold[11:0] $end
$var reg 12 j hysteresis[11:0] $end
$var reg 1 k interlock_active $end
$var reg 1 l fault_current $end
$var reg 1 m fault_voltage $end
$var reg 1 n fault_temperature $end
$var reg 12 o current_u[11:0] $end
$var reg 12 p voltage_u[11:0] $end
$var reg 12 q temperature_u[11:0] $end
$var reg 12 r current_thresh_u[11:0] $end
$var reg 12 s voltage_thresh_u[11:0] $end
$var reg 12 t temp_thresh_u[11:0] $end
$var reg 12 u hysteresis_u[11:0] $end
$var reg 1 v fault_current_int $end
$var reg 1 w fault_voltage_int $end
$var reg 1 x fault_temperature_int $end
$upscope $end
$scope module pwm_gen $end
$var reg 1 y clk $end
$var reg 1 z reset $end
$var reg 1 { enable $end
$var reg 8 | duty_cycle[7:0] $end
$var reg 1 } pwm_out $end
$var reg 8 !" counter[7:0] $end
$var reg 8 "" duty_unsigned[7:0] $end
$upscope $end
$upscope $end
$upscope $end
$enddefinitions $end
#0
0!
1"
0#
0$
0%
b10000000 &
b011111010000 '
b100111000100 (
b011111010000 )
b101110111000 *
b110110101100 +
b101011110000 ,
b000011001000 -
0.
1/
00
01
02
03
04
05
06
07
08
09
1:
0;
0<
0=
b10000000 >
b011111010000 ?
b100111000100 @
b011111010000 A
b101110111000 B
b110110101100 C
b101011110000 D
b000011001000 E
0F
1G
0H
0I
0J
0K
0L
0M
0N
0O
0P
0Q
0R
0S
0T
1U
0V
0W
0X
0Y
0Z
1[
0\
0]
0^
0_
b00000000 `
b00000000 a
0b
1c
b011111010000 d
b100111000100 e
b011111010000 f
b101110111000 g
b110110101100 h
b101011110000 i
b000011001000 j
0k
0l
0m
0n
b011111010000 o
b100111000100 p
b011111010000 q
b101110111000 r
b110110101100 s
b101011110000 t
b000011001000 u
0v
0w
0x
0y
1z
0{
b10000000 |
0}
b00000000 !"
b10000000 ""
#5000000
1!
19
1T
1b
1y
#10000000
0!
09
0T
0b
0y
#15000000
1!
19
1T
1b
1y
#20000000
0!
09
0T
0b
0y
#25000000
1!
19
1T
1b
1y
#30000000
0!
09
0T
0b
0y
#35000000
1!
19
1T
1b
1y
#40000000
0!
09
0T
0b
0y
#45000000
1!
19
1T
1b
1y
#50000000
0!
0"
09
0:
0T
0U
0b
0c
0y
0z
#55000000
1!
19
1T
1b
1y
#60000000
0!
09
0T
0b
0y
#65000000
1!
19
1T
1b
1y
#70000000
0!
09
0T
0b
0y
#75000000
1!
19
1T
1b
1y
#80000000
0!
09
0T
0b
0y
#85000000
1!
19
1T
1b
1y
#90000000
0!
09
0T
0b
0y
#95000000
1!
19
1T
1b
1y
#100000000
0!
1#
09
1;
0T
1V
0b
0y
#105000000
1!
0/
10
19
0G
1H
1T
0[
1\
1b
1y
#110000000
0!
09
0T
0b
0y
#115000000
1!
19
1T
b00000001 `
1b
1y
#120000000
0!
0#
09
0;
0T
0V
0b
0y
#125000000
1!
19
1T
b00000010 `
1b
1y
#130000000
0!
09
0T
0b
0y
#135000000
1!
19
1T
b00000011 `
1b
1y
#140000000
0!
09
0T
0b
0y
#145000000
1!
19
1T
b00000100 `
1b
1y
#150000000
0!
09
0T
0b
0y
#155000000
1!
19
1T
b00000101 `
1b
1y
#160000000
0!
09
0T
0b
0y
#165000000
1!
19
1T
b00000110 `
1b
1y
#170000000
0!
09
0T
0b
0y
#175000000
1!
19
1T
b00000111 `
1b
1y
#180000000
0!
09
0T
0b
0y
#185000000
1!
19
1T
b00001000 `
1b
1y
#190000000
0!
09
0T
0b
0y
#195000000
1!
19
1T
b00001001 `
1b
1y
#200000000
0!
09
0T
0b
0y
#205000000
1!
19
1T
b00001010 `
1b
1y
#210000000
0!
09
0T
0b
0y
#215000000
1!
19
1T
b00001011 `
1b
1y
#220000000
0!
09
0T
0b
0y
#225000000
1!
19
1T
b00001100 `
1b
1y
#230000000
0!
09
0T
0b
0y
#235000000
1!
19
1T
b00001101 `
1b
1y
#240000000
0!
09
0T
0b
0y
#245000000
1!
19
1T
b00001110 `
1b
1y
#250000000
0!
09
0T
0b
0y
#255000000
1!
19
1T
b00001111 `
1b
1y
#260000000
0!
09
0T
0b
0y
#265000000
1!
19
1T
b00010000 `
1b
1y
#270000000
0!
09
0T
0b
0y
#275000000
1!
19
1T
b00010001 `
1b
1y
#280000000
0!
09
0T
0b
0y
#285000000
1!
19
1T
b00010010 `
1b
1y
#290000000
0!
09
0T
0b
0y
#295000000
1!
19
1T
b00010011 `
1b
1y
#300000000
0!
09
0T
0b
0y
#305000000
1!
19
1T
b00010100 `
1b
1y
#310000000
0!
09
0T
0b
0y
#315000000
1!
19
1T
b00010101 `
1b
1y
#320000000
0!
09
0T
0b
0y
#325000000
1!
19
1T
b00010110 `
1b
1y
#330000000
0!
09
0T
0b
0y
#335000000
1!
19
1T
b00010111 `
1b
1y
#340000000
0!
09
0T
0b
0y
#345000000
1!
19
1T
b00011000 `
1b
1y
#350000000
0!
09
0T
0b
0y
#355000000
1!
19
1T
b00011001 `
1b
1y
#360000000
0!
09
0T
0b
0y
#365000000
1!
19
1T
b00011010 `
1b
1y
#370000000
0!
09
0T
0b
0y
#375000000
1!
19
1T
b00011011 `
1b
1y
#380000000
0!
09
0T
0b
0y
#385000000
1!
19
1T
b00011100 `
1b
1y
#390000000
0!
09
0T
0b
0y
#395000000
1!
19
1T
b00011101 `
1b
1y
#400000000
0!
09
0T
0b
0y
#405000000
1!
19
1T
b00011110 `
1b
1y
#410000000
0!
09
0T
0b
0y
#415000000
1!
19
1T
b00011111 `
1b
1y
#420000000
0!
09
0T
0b
0y
#425000000
1!
19
1T
b00100000 `
1b
1y
#430000000
0!
09
0T
0b
0y
#435000000
1!
19
1T
b00100001 `
1b
1y
#440000000
0!
09
0T
0b
0y
#445000000
1!
19
1T
b00100010 `
1b
1y
#450000000
0!
09
0T
0b
0y
#455000000
1!
19
1T
b00100011 `
1b
1y
#460000000
0!
09
0T
0b
0y
#465000000
1!
19
1T
b00100100 `
1b
1y
#470000000
0!
09
0T
0b
0y
#475000000
1!
19
1T
b00100101 `
1b
1y
#480000000
0!
09
0T
0b
0y
#485000000
1!
19
1T
b00100110 `
1b
1y
#490000000
0!
09
0T
0b
0y
#495000000
1!
19
1T
b00100111 `
1b
1y
#500000000
0!
09
0T
0b
0y
#505000000
1!
19
1T
b00101000 `
1b
1y
#510000000
0!
09
0T
0b
0y
#515000000
1!
19
1T
b00101001 `
1b
1y
#520000000
0!
09
0T
0b
0y
#525000000
1!
19
1T
b00101010 `
1b
1y
#530000000
0!
09
0T
0b
0y
#535000000
1!
19
1T
b00101011 `
1b
1y
#540000000
0!
09
0T
0b
0y
#545000000
1!
19
1T
b00101100 `
1b
1y
#550000000
0!
09
0T
0b
0y
#555000000
1!
19
1T
b00101101 `
1b
1y
#560000000
0!
09
0T
0b
0y
#565000000
1!
19
1T
b00101110 `
1b
1y
#570000000
0!
09
0T
0b
0y
#575000000
1!
19
1T
b00101111 `
1b
1y
#580000000
0!
09
0T
0b
0y
#585000000
1!
19
1T
b00110000 `
1b
1y
#590000000
0!
09
0T
0b
0y
#595000000
1!
19
1T
b00110001 `
1b
1y
#600000000
0!
09
0T
0b
0y
#605000000
1!
19
1T
b00110010 `
1b
1y
#610000000
0!
09
0T
0b
0y
#615000000
1!
00
11
19
0H
1I
1T
0\
1]
1b
1y
#620000000
0!
09
0T
0b
0y
#625000000
1!
19
1P
1Q
1T
1Z
b00000000 `
1b
1y
1{
#630000000
0!
09
0T
0b
0y
#635000000
1!
1.
19
1F
1S
1T
1Z
1b
1y
1}
b00000001 !"
#640000000
0!
09
0T
0b
0y
#645000000
1!
19
1T
1Z
1b
1y
b00000010 !"
#650000000
0!
09
0T
0b
0y
#655000000
1!
19
1T
1Z
1b
1y
b00000011 !"
#660000000
0!
09
0T
0b
0y
#665000000
1!
19
1T
1Z
1b
1y
b00000100 !"
#670000000
0!
09
0T
0b
0y
#675000000
1!
19
1T
1Z
1b
1y
b00000101 !"
#680000000
0!
09
0T
0b
0y
#685000000
1!
19
1T
1Z
1b
1y
b00000110 !"
#690000000
0!
09
0T
0b
0y
#695000000
1!
19
1T
1Z
1b
1y
b00000111 !"
#700000000
0!
09
0T
0b
0y
#705000000
1!
19
1T
1Z
1b
1y
b00001000 !"
#710000000
0!
09
0T
0b
0y
#715000000
1!
19
1T
1Z
1b
1y
b00001001 !"
#720000000
0!
09
0T
0b
0y
#725000000
1!
19
1T
1Z
1b
1y
b00001010 !"
#730000000
0!
09
0T
0b
0y
#735000000
1!
19
1T
1Z
1b
1y
b00001011 !"
#740000000
0!
09
0T
0b
0y
#745000000
1!
19
1T
1Z
1b
1y
b00001100 !"
#750000000
0!
09
0T
0b
0y
#755000000
1!
19
1T
1Z
1b
1y
b00001101 !"
#760000000
0!
09
0T
0b
0y
#765000000
1!
19
1T
1Z
1b
1y
b00001110 !"
#770000000
0!
09
0T
0b
0y
#775000000
1!
19
1T
1Z
1b
1y
b00001111 !"
#780000000
0!
09
0T
0b
0y
#785000000
1!
19
1T
1Z
1b
1y
b00010000 !"
#790000000
0!
09
0T
0b
0y
#795000000
1!
19
1T
1Z
1b
1y
b00010001 !"
#800000000
0!
09
0T
0b
0y
#805000000
1!
19
1T
1Z
1b
1y
b00010010 !"
#810000000
0!
09
0T
0b
0y
#815000000
1!
19
1T
1Z
1b
1y
b00010011 !"
#820000000
0!
09
0T
0b
0y
#825000000
1!
19
1T
1Z
1b
1y
b00010100 !"
#830000000
0!
09
0T
0b
0y
#835000000
1!
19
1T
1Z
1b
1y
b00010101 !"
#840000000
0!
09
0T
0b
0y
#845000000
1!
19
1T
1Z
1b
1y
b00010110 !"
#850000000
0!
09
0T
0b
0y
#855000000
1!
19
1T
1Z
1b
1y
b00010111 !"
#860000000
0!
09
0T
0b
0y
#865000000
1!
19
1T
1Z
1b
1y
b00011000 !"
#870000000
0!
09
0T
0b
0y
#875000000
1!
19
1T
1Z
1b
1y
b00011001 !"
#880000000
0!
09
0T
0b
0y
#885000000
1!
19
1T
1Z
1b
1y
b00011010 !"
#890000000
0!
09
0T
0b
0y
#895000000
1!
19
1T
1Z
1b
1y
b00011011 !"
#900000000
0!
09
0T
0b
0y
#905000000
1!
19
1T
1Z
1b
1y
b00011100 !"
