rtl/counter.vhdl
library ieee;
use ieee.std_logic_1164.all;
use ieee.numeric_std.all;

entity counter is
    port (
        clk     : in  std_logic;
        reset   : in  std_logic;
        enable  : in  std_logic;
        count   : out std_logic_vector(7 downto 0)
    );
end entity counter;

architecture rtl of counter is
    signal count_internal : unsigned(7 downto 0);
begin
    process(clk, reset)
    begin
        if reset = '1' then
            count_internal <= (others => '0');
        elsif rising_edge(clk) then
            if enable = '1' then
                count_internal <= count_internal + 1;
            end if;
        end if;
    end process;
    
    count <= std_logic_vector(count_internal);
end architecture rtl;

tb/counter_tb.vhdl
library ieee;
use ieee.std_logic_1164.all;

entity counter_tb is
end entity counter_tb;

architecture sim of counter_tb is
    -- Clock period
    constant CLK_PERIOD : time := 10 ns;
    
    -- Signals to connect to counter
    signal clk    : std_logic := '0';
    signal reset  : std_logic := '0';
    signal enable : std_logic := '0';
    signal count  : std_logic_vector(7 downto 0);
    
    -- Control simulation
    signal sim_done : boolean := false;
    
begin
    -- Instantiate the counter
    uut: entity work.counter
        port map (
            clk    => clk,
            reset  => reset,
            enable => enable,
            count  => count
        );
    
    -- Clock generation
    clk_gen: process
    begin
        while not sim_done loop
            clk <= '0';
            wait for CLK_PERIOD/2;
            clk <= '1';
            wait for CLK_PERIOD/2;
        end loop;
        wait;
    end process;
    
    -- Stimulus process
    stim: process
    begin
        -- Start with reset
        reset <= '1';
        enable <= '0';
        wait for 20 ns;
        
        -- Release reset
        reset <= '0';
        wait for 20 ns;
        
        -- Enable counting
        enable <= '1';
        wait for 200 ns;
        
        -- Disable counting
        enable <= '0';
        wait for 50 ns;
        
        -- Enable again
        enable <= '1';
        wait for 100 ns;
        
        -- Reset while counting
        reset <= '1';
        wait for 20 ns;
        reset <= '0';
        
        -- Count a bit more
        wait for 100 ns;
        
        -- End simulation
        sim_done <= true;
        wait;
    end process;
    
end architecture sim;

sim/counter.vcd
$date
  Thu Jan 29 13:39:59 2026
$end
$version
  GHDL v0
$end
$timescale
  1 fs
$end
$scope module standard $end
$upscope $end
$scope module std_logic_1164 $end
$upscope $end
$scope module numeric_std $end
$upscope $end
$scope module counter_tb $end
$var reg 1 ! clk $end
$var reg 1 " reset $end
$var reg 1 # enable $end
$var reg 8 $ count[7:0] $end
$var reg 1 % sim_done $end
$scope module uut $end
$var reg 1 & clk $end
$var reg 1 ' reset $end
$var reg 1 ( enable $end
$var reg 8 ) count[7:0] $end
$var reg 8 * count_internal[7:0] $end
$upscope $end
$upscope $end
$enddefinitions $end
#0
0!
1"
0#
b00000000 $
0%
0&
1'
0(
b00000000 )
b00000000 *
#5000000
1!
1&
#10000000
0!
0&
#15000000
1!
1&
#20000000
0!
0"
0&
0'
#25000000
1!
1&
#30000000
0!
0&
#35000000
1!
1&
#40000000
0!
1#
0&
1(
#45000000
1!
b00000001 $
1&
b00000001 )
b00000001 *
#50000000
0!
0&
#55000000
1!
b00000010 $
1&
b00000010 )
b00000010 *
#60000000
0!
0&
#65000000
1!
b00000011 $
1&
b00000011 )
b00000011 *
#70000000
0!
0&
#75000000
1!
b00000100 $
1&
b00000100 )
b00000100 *
#80000000
0!
0&
#85000000
1!
b00000101 $
1&
b00000101 )
b00000101 *
#90000000
0!
0&
#95000000
1!
b00000110 $
1&
b00000110 )
b00000110 *
#100000000
0!
0&
#105000000
1!
b00000111 $
1&
b00000111 )
b00000111 *
#110000000
0!
0&
#115000000
1!
b00001000 $
1&
b00001000 )
b00001000 *
#120000000
0!
0&
#125000000
1!
b00001001 $
1&
b00001001 )
b00001001 *
#130000000
0!
0&
#135000000
1!
b00001010 $
1&
b00001010 )
b00001010 *
#140000000
0!
0&
#145000000
1!
b00001011 $
1&
b00001011 )
b00001011 *
#150000000
0!
0&
#155000000
1!
b00001100 $
1&
b00001100 )
b00001100 *
#160000000
0!
0&
#165000000
1!
b00001101 $
1&
b00001101 )
b00001101 *
#170000000
0!
0&
#175000000
1!
b00001110 $
1&
b00001110 )
b00001110 *
#180000000
0!
0&
#185000000
1!
b00001111 $
1&
b00001111 )
b00001111 *
#190000000
0!
0&
#195000000
1!
b00010000 $
1&
b00010000 )
b00010000 *
#200000000
0!
0&
#205000000
1!
b00010001 $
1&
b00010001 )
b00010001 *
#210000000
0!
0&
#215000000
1!
b00010010 $
1&
b00010010 )
b00010010 *
#220000000
0!
0&
#225000000
1!
b00010011 $
1&
b00010011 )
b00010011 *
#230000000
0!
0&
#235000000
1!
b00010100 $
1&
b00010100 )
b00010100 *
#240000000
0!
0#
0&
0(
#245000000
1!
1&
#250000000
0!
0&
#255000000
1!
1&
#260000000
0!
0&
#265000000
1!
1&
#270000000
0!
0&
#275000000
1!
1&
#280000000
0!
0&
#285000000
1!
1&
#290000000
0!
1#
0&
1(
#295000000
1!
b00010101 $
1&
b00010101 )
b00010101 *
#300000000
0!
0&
#305000000
1!
b00010110 $
1&
b00010110 )
b00010110 *
#310000000
0!
0&
#315000000
1!
b00010111 $
1&
b00010111 )
b00010111 *
#320000000
0!
0&
#325000000
1!
b00011000 $
1&
b00011000 )
b00011000 *
#330000000
0!
0&
#335000000
1!
b00011001 $
1&
b00011001 )
b00011001 *
#340000000
0!
0&
#345000000
1!
b00011010 $
1&
b00011010 )
b00011010 *
#350000000
0!
0&
#355000000
1!
b00011011 $
1&
b00011011 )
b00011011 *
#360000000
0!
0&
#365000000
1!
b00011100 $
1&
b00011100 )
b00011100 *
#370000000
0!
0&
#375000000
1!
b00011101 $
1&
b00011101 )
b00011101 *
#380000000
0!
0&
#385000000
1!
b00011110 $
1&
b00011110 )
b00011110 *
#390000000
0!
1"
b00000000 $
0&
1'
b00000000 )
b00000000 *
#395000000
1!
1&
#400000000
0!
0&
#405000000
1!
1&
#410000000
0!
0"
0&
0'
#415000000
1!
b00000001 $
1&
b00000001 )
b00000001 *
#420000000
0!
0&
#425000000
1!
b00000010 $
1&
b00000010 )
b00000010 *
#430000000
0!
0&
#435000000
1!
b00000011 $
1&
b00000011 )
b00000011 *
#440000000
0!
0&
#445000000
1!
b00000100 $
1&
b00000100 )
b00000100 *
#450000000
0!
0&
#455000000
1!
b00000101 $
1&
b00000101 )
b00000101 *
#460000000
0!
0&
#465000000
1!
b00000110 $
1&
b00000110 )
b00000110 *
#470000000
0!
0&
#475000000
1!
b00000111 $
1&
b00000111 )
b00000111 *
#480000000
0!
0&
#485000000
1!
b00001000 $
1&
b00001000 )
b00001000 *
#490000000
0!
0&
#495000000
1!
b00001001 $
1&
b00001001 )
b00001001 *
#500000000
0!
0&
#505000000
1!
b00001010 $
1&
b00001010 )
b00001010 *
#510000000
0!
1%
0&
#515000000
1!
b00001011 $
1&
b00001011 )
b00001011 *
