rtl/power_controller_fsm.vhdl
library ieee;
use ieee.std_logic_1164.all;
use ieee.numeric_std.all;

entity power_controller_fsm is
    port (
        clk              : in  std_logic;
        reset            : in  std_logic;
        
        -- Control inputs
        start_cmd        : in  std_logic;  -- User command to start
        stop_cmd         : in  std_logic;  -- User command to stop
        fault_ack        : in  std_logic;  -- Acknowledge fault to allow restart
        
        -- Status inputs
        interlock_active : in  std_logic;  -- From interlock system
        
        -- Outputs
        pwm_enable       : out std_logic;  -- Enable PWM generator
        state_idle       : out std_logic;  -- State indicators
        state_startup    : out std_logic;
        state_running    : out std_logic;
        state_fault      : out std_logic;
        state_shutdown   : out std_logic
    );
end entity power_controller_fsm;

architecture rtl of power_controller_fsm is
    -- State type definition
    type state_type is (IDLE, STARTUP, RUNNING, FAULT, SHUTDOWN);
    signal current_state : state_type;
    signal next_state    : state_type;
    
    -- Startup delay counter (simulates pre-charge time)
    signal startup_counter : unsigned(7 downto 0);
    constant STARTUP_DELAY : unsigned(7 downto 0) := to_unsigned(50, 8);  -- 50 clock cycles
    
    -- Shutdown delay counter
    signal shutdown_counter : unsigned(7 downto 0);
    constant SHUTDOWN_DELAY : unsigned(7 downto 0) := to_unsigned(30, 8);  -- 30 clock cycles
    
begin
    -- State register (sequential logic)
    process(clk, reset)
    begin
        if reset = '1' then
            current_state <= IDLE;
        elsif rising_edge(clk) then
            current_state <= next_state;
        end if;
    end process;
    
    -- Next state logic (combinational)
    process(current_state, start_cmd, stop_cmd, fault_ack, interlock_active, 
            startup_counter, shutdown_counter)
    begin
        -- Default: stay in current state
        next_state <= current_state;
        
        case current_state is
            when IDLE =>
                if start_cmd = '1' and interlock_active = '0' then
                    next_state <= STARTUP;
                end if;
            
            when STARTUP =>
                -- Check for faults during startup
                if interlock_active = '1' then
                    next_state <= FAULT;
                -- Wait for startup delay to complete
                elsif startup_counter >= STARTUP_DELAY then
                    next_state <= RUNNING;
                end if;
            
            when RUNNING =>
                -- Priority 1: Fault detection
                if interlock_active = '1' then
                    next_state <= FAULT;
                -- Priority 2: Stop command
                elsif stop_cmd = '1' then
                    next_state <= SHUTDOWN;
                end if;
            
            when FAULT =>
                -- Must acknowledge fault AND fault must be cleared to restart
                if fault_ack = '1' and interlock_active = '0' then
                    next_state <= IDLE;
                end if;
            
            when SHUTDOWN =>
                -- Wait for shutdown delay, then return to idle
                if shutdown_counter >= SHUTDOWN_DELAY then
                    next_state <= IDLE;
                end if;
        end case;
    end process;
    
    -- Output logic and counters (sequential)
    process(clk, reset)
    begin
        if reset = '1' then
            pwm_enable       <= '0';
            startup_counter  <= (others => '0');
            shutdown_counter <= (others => '0');
            
        elsif rising_edge(clk) then
            -- Default outputs
            pwm_enable <= '0';
            
            case current_state is
                when IDLE =>
                    startup_counter  <= (others => '0');
                    shutdown_counter <= (others => '0');
                
                when STARTUP =>
                    -- Increment startup counter
                    if startup_counter < STARTUP_DELAY then
                        startup_counter <= startup_counter + 1;
                    end if;
                    -- PWM disabled during startup
                    pwm_enable <= '0';
                
                when RUNNING =>
                    -- Enable PWM in running state
                    pwm_enable <= '1';
                    startup_counter  <= (others => '0');
                    shutdown_counter <= (others => '0');
                
                when FAULT =>
                    -- Immediately disable PWM
                    pwm_enable <= '0';
                    startup_counter  <= (others => '0');
                    shutdown_counter <= (others => '0');
                
                when SHUTDOWN =>
                    -- Increment shutdown counter
                    if shutdown_counter < SHUTDOWN_DELAY then
                        shutdown_counter <= shutdown_counter + 1;
                    end if;
                    -- PWM disabled during shutdown
                    pwm_enable <= '0';
            end case;
        end if;
    end process;
    
    -- State indicator outputs (for monitoring/debugging)
    state_idle     <= '1' when current_state = IDLE     else '0';
    state_startup  <= '1' when current_state = STARTUP  else '0';
    state_running  <= '1' when current_state = RUNNING  else '0';
    state_fault    <= '1' when current_state = FAULT    else '0';
    state_shutdown <= '1' when current_state = SHUTDOWN else '0';
    
end architecture rtl;

tb/power_controller_fsm_tb.vhdl
library ieee;
use ieee.std_logic_1164.all;

entity power_controller_fsm_tb is
end entity power_controller_fsm_tb;

architecture sim of power_controller_fsm_tb is
    constant CLK_PERIOD : time := 10 ns;
    
    signal clk              : std_logic := '0';
    signal reset            : std_logic := '0';
    signal start_cmd        : std_logic := '0';
    signal stop_cmd         : std_logic := '0';
    signal fault_ack        : std_logic := '0';
    signal interlock_active : std_logic := '0';
    signal pwm_enable       : std_logic;
    signal state_idle       : std_logic;
    signal state_startup    : std_logic;
    signal state_running    : std_logic;
    signal state_fault      : std_logic;
    signal state_shutdown   : std_logic;
    
    signal sim_done : boolean := false;
    
begin
    -- Instantiate FSM
    uut: entity work.power_controller_fsm
        port map (
            clk              => clk,
            reset            => reset,
            start_cmd        => start_cmd,
            stop_cmd         => stop_cmd,
            fault_ack        => fault_ack,
            interlock_active => interlock_active,
            pwm_enable       => pwm_enable,
            state_idle       => state_idle,
            state_startup    => state_startup,
            state_running    => state_running,
            state_fault      => state_fault,
            state_shutdown   => state_shutdown
        );
    
    -- Clock generation
    clk_gen: process
    begin
        while not sim_done loop
            clk <= '0';
            wait for CLK_PERIOD/2;
            clk <= '1';
            wait for CLK_PERIOD/2;
        end loop;
        wait;
    end process;
    
    -- Stimulus
    stim: process
    begin
        -- Initialize
        reset <= '1';
        wait for 50 ns;
        reset <= '0';
        wait for 50 ns;
        
        -- Test 1: Normal startup sequence
        report "Test 1: Normal startup sequence";
        start_cmd <= '1';
        wait for 20 ns;
        start_cmd <= '0';
        wait for 600 ns;  -- Wait through startup delay
        
        -- Test 2: Normal operation
        report "Test 2: Running normally";
        wait for 500 ns;
        
        -- Test 3: Normal shutdown
        report "Test 3: Normal shutdown";
        stop_cmd <= '1';
        wait for 20 ns;
        stop_cmd <= '0';
        wait for 400 ns;  -- Wait through shutdown delay
        
        -- Test 4: Start again
        report "Test 4: Restart after shutdown";
        start_cmd <= '1';
        wait for 20 ns;
        start_cmd <= '0';
        wait for 600 ns;
        
        -- Test 5: Fault during operation
        report "Test 5: Fault occurs during running";
        interlock_active <= '1';
        wait for 300 ns;
        
        -- Test 6: Try to restart without acknowledging (should stay in fault)
        report "Test 6: Try restart without ack (should fail)";
        start_cmd <= '1';
        wait for 20 ns;
        start_cmd <= '0';
        wait for 200 ns;
        
        -- Test 7: Clear fault but don't acknowledge
        report "Test 7: Clear fault, still need ack";
        interlock_active <= '0';
        wait for 200 ns;
        
        -- Test 8: Acknowledge fault (should return to idle)
        report "Test 8: Acknowledge fault";
        fault_ack <= '1';
        wait for 20 ns;
        fault_ack <= '0';
        wait for 100 ns;
        
        -- Test 9: Restart after fault cleared
        report "Test 9: Restart after fault cleared";
        start_cmd <= '1';
        wait for 20 ns;
        start_cmd <= '0';
        wait for 600 ns;
        
        -- Test 10: Fault during startup
        report "Test 10: Fault during startup";
        stop_cmd <= '1';
        wait for 20 ns;
        stop_cmd <= '0';
        wait for 400 ns;
        
        start_cmd <= '1';
        wait for 20 ns;
        start_cmd <= '0';
        wait for 200 ns;  -- Partway through startup
        
        interlock_active <= '1';  -- Fault!
        wait for 300 ns;
        
        -- Clear and acknowledge
        interlock_active <= '0';
        wait for 50 ns;
        fault_ack <= '1';
        wait for 20 ns;
        fault_ack <= '0';
        wait for 100 ns;
        
        -- End simulation
        report "Simulation complete";
        sim_done <= true;
        wait;
    end process;
    
end architecture sim;

sim/fsm.vcd
$date
  Thu Jan 29 13:40:00 2026
$end
$version
  GHDL v0
$end
$timescale
  1 fs
$end
$scope module standard $end
$upscope $end
$scope module std_logic_1164 $end
$upscope $end
$scope module numeric_std $end
$upscope $end
$scope module power_controller_fsm_tb $end
$var reg 1 ! clk $end
$var reg 1 " reset $end
$var reg 1 # start_cmd $end
$var reg 1 $ stop_cmd $end
$var reg 1 % fault_ack $end
$var reg 1 & interlock_active $end
$var reg 1 ' pwm_enable $end
$var reg 1 ( state_idle $end
$var reg 1 ) state_startup $end
$var reg 1 * state_running $end
$var reg 1 + state_fault $end
$var reg 1 , state_shutdown $end
$var reg 1 - sim_done $end
$scope module uut $end
$var reg 1 . clk $end
$var reg 1 / reset $end
$var reg 1 0 start_cmd $end
$var reg 1 1 stop_cmd $end
$var reg 1 2 fault_ack $end
$var reg 1 3 interlock_active $end
$var reg 1 4 pwm_enable $end
$var reg 1 5 state_idle $end
$var reg 1 6 state_startup $end
$var reg 1 7 state_running $end
$var reg 1 8 state_fault $end
$var reg 1 9 state_shutdown $end
$comment current_state is not handled $end
$comment next_state is not handled $end
$var reg 8 : startup_counter[7:0] $end
$var reg 8 ; shutdown_counter[7:0] $end
$upscope $end
$upscope $end
$enddefinitions $end
#0
0!
1"
0#
0$
0%
0&
0'
1(
0)
0*
0+
0,
0-
0.
1/
00
01
02
03
04
15
06
07
08
09
b00000000 :
b00000000 ;
#5000000
1!
1.
#10000000
0!
0.
#15000000
1!
1.
#20000000
0!
0.
#25000000
1!
1.
#30000000
0!
0.
#35000000
1!
1.
#40000000
0!
0.
#45000000
1!
1.
#50000000
0!
0"
0.
0/
#55000000
1!
1.
#60000000
0!
0.
#65000000
1!
1.
#70000000
0!
0.
#75000000
1!
1.
#80000000
0!
0.
#85000000
1!
1.
#90000000
0!
0.
#95000000
1!
1.
#100000000
0!
1#
0.
10
#105000000
1!
0(
1)
1.
05
16
#110000000
0!
0.
#115000000
1!
1.
b00000001 :
#120000000
0!
0#
0.
00
#125000000
1!
1.
b00000010 :
#130000000
0!
0.
#135000000
1!
1.
b00000011 :
#140000000
0!
0.
#145000000
1!
1.
b00000100 :
#150000000
0!
0.
#155000000
1!
1.
b00000101 :
#160000000
0!
0.
#165000000
1!
1.
b00000110 :
#170000000
0!
0.
#175000000
1!
1.
b00000111 :
#180000000
0!
0.
#185000000
1!
1.
b00001000 :
#190000000
0!
0.
#195000000
1!
1.
b00001001 :
#200000000
0!
0.
#205000000
1!
1.
b00001010 :
#210000000
0!
0.
#215000000
1!
1.
b00001011 :
#220000000
0!
0.
#225000000
1!
1.
b00001100 :
#230000000
0!
0.
#235000000
1!
1.
b00001101 :
#240000000
0!
0.
#245000000
1!
1.
b00001110 :
#250000000
0!
0.
#255000000
1!
1.
b00001111 :
#260000000
0!
0.
#265000000
1!
1.
b00010000 :
#270000000
0!
0.
#275000000
1!
1.
b00010001 :
#280000000
0!
0.
#285000000
1!
1.
b00010010 :
#290000000
0!
0.
#295000000
1!
1.
b00010011 :
#300000000
0!
0.
#305000000
1!
1.
b00010100 :
#310000000
0!
0.
#315000000
1!
1.
b00010101 :
#320000000
0!
0.
#325000000
1!
1.
b00010110 :
#330000000
0!
0.
#335000000
1!
1.
b00010111 :
#340000000
0!
0.
#345000000
1!
1.
b00011000 :
#350000000
0!
0.
#355000000
1!
1.
b00011001 :
#360000000
0!
0.
#365000000
1!
1.
b00011010 :
#370000000
0!
0.
#375000000
1!
1.
b00011011 :
#380000000
0!
0.
#385000000
1!
1.
b00011100 :
#390000000
0!
0.
#395000000
1!
1.
b00011101 :
#400000000
0!
0.
#405000000
1!
1.
b00011110 :
#410000000
0!
0.
#415000000
1!
1.
b00011111 :
#420000000
0!
0.
#425000000
1!
1.
b00100000 :
#430000000
0!
0.
#435000000
1!
1.
b00100001 :
#440000000
0!
0.
#445000000
1!
1.
b00100010 :
#450000000
0!
0.
#455000000
1!
1.
b00100011 :
#460000000
0!
0.
#465000000
1!
1.
b00100100 :
#470000000
0!
0.
#475000000
1!
1.
b00100101 :
#480000000
0!
0.
#485000000
1!
1.
b00100110 :
#490000000
0!
0.
#495000000
1!
1.
b00100111 :
#500000000
0!
0.
#505000000
1!
1.
b00101000 :
#510000000
0!
0.
#515000000
1!
1.
b00101001 :
#520000000
0!
0.
#525000000
1!
1.
b00101010 :
#530000000
0!
0.
#535000000
1!
1.
b00101011 :
#540000000
0!
0.
#545000000
1!
1.
b00101100 :
#550000000
0!
0.
#555000000
1!
1.
b00101101 :
#560000000
0!
0.
#565000000
1!
1.
b00101110 :
#570000000
0!
0.
#575000000
1!
1.
b00101111 :
#580000000
0!
0.
#585000000
1!
1.
b00110000 :
#590000000
0!
0.
#595000000
1!
1.
b00110001 :
#600000000
0!
0.
#605000000
1!
1.
b00110010 :
#610000000
0!
0.
#615000000
1!
0)
1*
1.
06
17
#620000000
0!
0.
#625000000
1!
1'
1.
14
b00000000 :
#630000000
0!
0.
#635000000
1!
1.
14
#640000000
0!
0.
#645000000
1!
1.
14
#650000000
0!
0.
#655000000
1!
1.
14
#660000000
0!
0.
#665000000
1!
1.
14
#670000000
0!
0.
#675000000
1!
1.
14
#680000000
0!
0.
#685000000
1!
1.
14
#690000000
0!
0.
#695000000
1!
1.
14
#700000000
0!
0.
#705000000
1!
1.
14
#710000000
0!
0.
#715000000
1!
1.
14
#720000000
0!
0.
#725000000
1!
1.
14
#730000000
0!
0.
#735000000
1!
1.
14
#740000000
0!
0.
#745000000
1!
1.
14
#750000000
0!
0.
#755000000
1!
1.
14
#760000000
0!
0.
#765000000
1!
1.
14
#770000000
0!
0.
#775000000
1!
1.
14
#780000000
0!
0.
#785000000
1!
1.
14
#790000000
0!
0.
#795000000
1!
1.
14
#800000000
0!
0.
#805000000
1!
1.
14
#810000000
0!
0.
#815000000
1!
1.
14
#820000000
0!
0.
#825000000
1!
1.
14
#830000000
0!
0.
#835000000
1!
1.
14
#840000000
0!
0.
#845000000
1!
1.
14
#850000000
0!
0.
#855000000
1!
1.
14
#860000000
0!
0.
#865000000
1!
1.
14
#870000000
0!
0.
#875000000
1!
1.
14
#880000000
0!
0.
#885000000
1!
1.
14
#890000000
0!
0.
#895000000
1!
1.
14
#900000000
0!
0.
#905000000
1!
1.
14
#910000000
0!
0.
#915000000
1!
1.
14
#920000000
0!
0.
#925000000
1!
1.
14
#930000000
0!
0.
#935000000
1!
1.
14
#940000000
0!
0.
#945000000
1!
1.
14
#950000000
0!
0.
#955000000
1!
1.
14
#960000000
0!
0.
#965000000
1!
1.
14
#970000000
0!
0.
#975000000
1!
1.
14
#980000000
0!
0.
#985000000
1!
1.
14
#990000000
0!
0.
#995000000
1!
1.
14
#1000000000
0!
0.
#1005000000
1!
1.
14
#1010000000
0!
0.
#1015000000
1!
1.
14
#1020000000
0!
0.
#1025000000
1!
1.
14
#1030000000
0!
0.
#1035000000
1!
1.
14
#1040000000
0!
0.
#1045000000
1!
1.
14
#1050000000
0!
0.
#1055000000
1!
1.
14
#1060000000
0!
0.
#1065000000
1!
1.
14
#1070000000
0!
0.
#1075000000
1!
1.
14
#1080000000
0!
0.
#1085000000
1!
1.
14
#1090000000
0!
0.
#1095000000
1!
1.
14
#1100000000
0!
0.
#1105000000
1!
1.
14
#1110000000
0!
0.
#1115000000
1!
1.
14
#1120000000
0!
0.
#1125000000
1!
1.
14
#1130000000
0!
0.
#1135000000
1!
1.
14
#1140000000
0!
0.
#1145000000
1!
1.
14
#1150000000
0!
0.
#1155000000
1!
1.
14
#1160000000
0!
0.
#1165000000
1!
1.
14
#1170000000
0!
0.
#1175000000
1!
1.
14
#1180000000
0!
0.
#1185000000
1!
1.
14
#1190000000
0!
0.
#1195000000
1!
1.
14
#1200000000
0!
0.
#1205000000
1!
1.
14
#1210000000
0!
0.
#1215000000
1!
1.
14
#1220000000
0!
1$
0.
11
#1225000000
1!
0*
1,
1.
14
07
19
#1230000000
0!
0.
#1235000000
1!
0'
1.
04
b00000001 ;
#1240000000
0!
0$
0.
01
#1245000000
1!
1.
b00000010 ;
#1250000000
0!
0.
#1255000000
1!
1.
b00000011 ;
#1260000000
0!
0.
#1265000000
1!
1.
b00000100 ;
#1270000000
0!
0.
#1275000000
1!
1.
b00000101 ;
#1280000000
0!
0.
#1285000000
1!
1.
b00000110 ;
#1290000000
0!
0.
#1295000000
1!
1.
b00000111 ;
#1300000000
0!
0.
#1305000000
1!
1.
b00001000 ;
#1310000000
0!
0.
#1315000000
1!
1.
b00001001 ;
#1320000000
0!
0.
#1325000000
1!
1.
b00001010 ;
#1330000000
0!
0.
#1335000000
1!
1.
b00001011 ;
#1340000000
0!
0.
#1345000000
1!
1.
b00001100 ;
#1350000000
0!
0.
#1355000000
1!
1.
b00001101 ;
#1360000000
0!
0.
#1365000000
1!
1.
b00001110 ;
#1370000000
0!
0.
#1375000000
1!
1.
b00001111 ;
#1380000000
0!
0.
#1385000000
1!
1.
b00010000 ;
#1390000000
0!
0.
#1395000000
1!
1.
b00010001 ;
#1400000000
0!
0.
#1405000000
1!
1.
b00010010 ;
#1410000000
0!
0.
#1415000000
1!
1.
b00010011 ;
#1420000000
0!
0.
#1425000000
1!
1.
b00010100 ;
#1430000000
0!
0.
#1435000000
1!
1.
b00010101 ;
#1440000000
0!
0.
#1445000000
1!
1.
b00010110 ;
#1450000000
0!
0.
#1455000000
1!
1.
b00010111 ;
#1460000000
0!
0.
#1465000000
1!
1.
b00011000 ;
#1470000000
0!
0.
#1475000000
1!
1.
b00011001 ;
#1480000000
0!
0.
#1485000000
1!
1.
b00011010 ;
#1490000000
0!
0.
#1495000000
1!
1.
b00011011 ;
#1500000000
0!
0.
#1505000000
1!
1.
b00011100 ;
#1510000000
0!
0.
#1515000000
1!
1.
b00011101 ;
#1520000000
0!
0.
#1525000000
1!
1.
b00011110 ;
#1530000000
0!
0.
#1535000000
1!
1(
0,
1.
15
09
#1540000000
0!
0.
#1545000000
1!
1.
b00000000 ;
#1550000000
0!
0.
#1555000000
1!
1.
#1560000000
0!
0.
#1565000000
1!
1.
#1570000000
0!
0.
#1575000000
1!
1.
#1580000000
0!
0.
#1585000000
1!
1.
#1590000000
0!
0.
#1595000000
1!
1.
#1600000000
0!
0.
#1605000000
1!
1.
#1610000000
0!
0.
#1615000000
1!
1.
#1620000000
0!
0.
#1625000000
1!
1.
#1630000000
0!
0.
#1635000000
1!
1.
#1640000000
0!
1#
0.
10
#1645000000
1!
0(
1)
1.
05
16
#1650000000
0!
0.
#1655000000
1!
1.
b00000001 :
#1660000000
0!
0#
0.
00
#1665000000
1!
1.
b00000010 :
#1670000000
0!
0.
#1675000000
1!
1.
b00000011 :
#1680000000
0!
0.
#1685000000
1!
1.
b00000100 :
#1690000000
0!
0.
#1695000000
1!
1.
b00000101 :
#1700000000
0!
0.
#1705000000
1!
1.
b00000110 :
#1710000000
0!
0.
#1715000000
1!
1.
b00000111 :
#1720000000
0!
0.
#1725000000
1!
1.
b00001000 :
#1730000000
0!
0.
#1735000000
1!
1.
b00001001 :
#1740000000
0!
0.
#1745000000
1!
1.
b00001010 :
#1750000000
0!
0.
#1755000000
1!
1.
b00001011 :
#1760000000
0!
0.
#1765000000
1!
1.
b00001100 :
#1770000000
0!
0.
#1775000000
1!
1.
b00001101 :
#1780000000
0!
0.
#1785000000
1!
1.
b00001110 :
#1790000000
0!
0.
#1795000000
1!
1.
b00001111 :
#1800000000
0!
0.
#1805000000
1!
1.
b00010000 :
#1810000000
0!
0.
#1815000000
1!
1.
b00010001 :
#1820000000
0!
0.
#1825000000
1!
1.
b00010010 :
#1830000000
0!
0.
#1835000000
1!
1.
b00010011 :
#1840000000
0!
0.
#1845000000
1!
1.
b00010100 :
#1850000000
0!
0.
#1855000000
1!
1.
b00010101 :
#1860000000
0!
0.
#1865000000
1!
1.
b00010110 :
#1870000000
0!
0.
#1875000000
1!
1.
b00010111 :
#1880000000
0!
0.
#1885000000
1!
1.
b00011000 :
#1890000000
0!
0.
#1895000000
1!
1.
b00011001 :
#1900000000
0!
0.
#1905000000
1!
1.
b00011010 :
#1910000000
0!
0.
#1915000000
1!
1.
b00011011 :
#1920000000
0!
0.
#1925000000
1!
1.
b00011100 :
#1930000000
0!
0.
#1935000000
1!
1.
b00011101 :
#1940000000
0!
0.
#1945000000
1!
1.
b00011110 :
#1950000000
0!
0.
#1955000000
1!
1.
b00011111 :
#1960000000
0!
0.
#1965000000
1!
1.
b00100000 :
#1970000000
0!
0.
#1975000000
1!
1.
b00100001 :
#1980000000
0!
0.
#1985000000
1!
1.
b00100010 :
#1990000000
0!
0.
#1995000000
1!
1.
b00100011 :
#2000000000
0!
0.
#2005000000
1!
1.
b00100100 :
#2010000000
0!
0.
#2015000000
1!
1.
b00100101 :
#2020000000
0!
0.
#2025000000
1!
1.
b00100110 :
#2030000000
0!
0.
#2035000000
1!
1.
b00100111 :
#2040000000
0!
0.
#2045000000
1!
1.
b00101000 :
#2050000000
0!
0.
#2055000000
1!
1.
b00101001 :
#2060000000
0!
0.
#2065000000
1!
1.
b00101010 :
#2070000000
0!
0.
#2075000000
1!
1.
b00101011 :
#2080000000
0!
0.
#2085000000
1!
1.
b00101100 :
#2090000000
0!
0.
#2095000000
1!
1.
b00101101 :
#2100000000
0!
0.
#2105000000
1!
1.
b00101110 :
#2110000000
0!
0.
#2115000000
1!
1.
b00101111 :
#2120000000
0!
0.
#2125000000
1!
1.
b00110000 :
#2130000000
0!
0.
#2135000000
1!
1.
b00110001 :
#2140000000
0!
0.
#2145000000
1!
1.
b00110010 :
#2150000000
0!
0.
#2155000000
1!
0)
1*
1.
06
17
#2160000000
0!
0.
#2165000000
1!
1'
1.
14
b00000000 :
#2170000000
0!
0.
#2175000000
1!
1.
14
#2180000000
0!
0.
#2185000000
1!
1.
14
#2190000000
0!
0.
#2195000000
1!
1.
14
#2200000000
0!
0.
#2205000000
1!
1.
14
#2210000000
0!
0.
#2215000000
1!
1.
14
#2220000000
0!
0.
#2225000000
1!
1.
14
#2230000000
0!
0.
#2235000000
1!
1.
14
#2240000000
0!
0.
#2245000000
1!
1.
14
#2250000000
0!
0.
#2255000000
1!
1.
14
#2260000000
0!
1&
0.
13
#2265000000
1!
0*
1+
1.
14
07
18
#2270000000
0!
0.
#2275000000
1!
0'
1.
04
