rtl/interlock.vhdl
library ieee;
use ieee.std_logic_1164.all;
use ieee.numeric_std.all;

entity interlock is
    generic (
        SENSOR_WIDTH : integer := 12  -- 12-bit ADC values (0-4095)
    );
    port (
        clk                : in  std_logic;
        reset              : in  std_logic;
        
        -- Sensor inputs (from ADCs measuring current, voltage, temp)
        current_value      : in  std_logic_vector(SENSOR_WIDTH-1 downto 0);
        voltage_value      : in  std_logic_vector(SENSOR_WIDTH-1 downto 0);
        temperature_value  : in  std_logic_vector(SENSOR_WIDTH-1 downto 0);
        
        -- Threshold settings
        current_threshold  : in  std_logic_vector(SENSOR_WIDTH-1 downto 0);
        voltage_threshold  : in  std_logic_vector(SENSOR_WIDTH-1 downto 0);
        temp_threshold     : in  std_logic_vector(SENSOR_WIDTH-1 downto 0);
        
        -- Hysteresis (threshold - hysteresis = clear level)
        hysteresis         : in  std_logic_vector(SENSOR_WIDTH-1 downto 0);
        
        -- Outputs
        interlock_active   : out std_logic;  -- '1' = fault detected, disable PWM
        fault_current      : out std_logic;  -- Which fault occurred
        fault_voltage      : out std_logic;
        fault_temperature  : out std_logic
    );
end entity interlock;

architecture rtl of interlock is
    -- Convert to unsigned for comparison
    signal current_u      : unsigned(SENSOR_WIDTH-1 downto 0);
    signal voltage_u      : unsigned(SENSOR_WIDTH-1 downto 0);
    signal temperature_u  : unsigned(SENSOR_WIDTH-1 downto 0);
    
    signal current_thresh_u  : unsigned(SENSOR_WIDTH-1 downto 0);
    signal voltage_thresh_u  : unsigned(SENSOR_WIDTH-1 downto 0);
    signal temp_thresh_u     : unsigned(SENSOR_WIDTH-1 downto 0);
    signal hysteresis_u      : unsigned(SENSOR_WIDTH-1 downto 0);
    
    -- Fault flags (internal)
    signal fault_current_int      : std_logic;
    signal fault_voltage_int      : std_logic;
    signal fault_temperature_int  : std_logic;
    
begin
    -- Type conversions
    current_u       <= unsigned(current_value);
    voltage_u       <= unsigned(voltage_value);
    temperature_u   <= unsigned(temperature_value);
    
    current_thresh_u  <= unsigned(current_threshold);
    voltage_thresh_u  <= unsigned(voltage_threshold);
    temp_thresh_u     <= unsigned(temp_threshold);
    hysteresis_u      <= unsigned(hysteresis);
    
    -- Main interlock logic with hysteresis
    process(clk, reset)
        variable clear_current_thresh  : unsigned(SENSOR_WIDTH-1 downto 0);
        variable clear_voltage_thresh  : unsigned(SENSOR_WIDTH-1 downto 0);
        variable clear_temp_thresh     : unsigned(SENSOR_WIDTH-1 downto 0);
    begin
        if reset = '1' then
            fault_current_int     <= '0';
            fault_voltage_int     <= '0';
            fault_temperature_int <= '0';
            
        elsif rising_edge(clk) then
            -- Calculate clear thresholds (trip - hysteresis)
            clear_current_thresh := current_thresh_u - hysteresis_u;
            clear_voltage_thresh := voltage_thresh_u - hysteresis_u;
            clear_temp_thresh    := temp_thresh_u - hysteresis_u;
            
            -- Current interlock with hysteresis
            if current_u >= current_thresh_u then
                fault_current_int <= '1';  -- Trip
            elsif current_u < clear_current_thresh then
                fault_current_int <= '0';  -- Clear
            end if;
            -- Otherwise maintain current state (hysteresis region)
            
            -- Voltage interlock with hysteresis
            if voltage_u >= voltage_thresh_u then
                fault_voltage_int <= '1';
            elsif voltage_u < clear_voltage_thresh then
                fault_voltage_int <= '0';
            end if;
            
            -- Temperature interlock with hysteresis
            if temperature_u >= temp_thresh_u then
                fault_temperature_int <= '1';
            elsif temperature_u < clear_temp_thresh then
                fault_temperature_int <= '0';
            end if;
        end if;
    end process;
    
    -- Output assignment (combinational for fastest response)
    interlock_active  <= fault_current_int or fault_voltage_int or fault_temperature_int;
    fault_current     <= fault_current_int;
    fault_voltage     <= fault_voltage_int;
    fault_temperature <= fault_temperature_int;
    
end architecture rtl;

tb/interlock_tb.vhdl
library ieee;
use ieee.std_logic_1164.all;
use ieee.numeric_std.all;

entity interlock_tb is
end entity interlock_tb;

architecture sim of interlock_tb is
    constant CLK_PERIOD : time := 10 ns;
    constant SENSOR_WIDTH : integer := 12;
    
    signal clk               : std_logic := '0';
    signal reset             : std_logic := '0';
    signal current_value     : std_logic_vector(SENSOR_WIDTH-1 downto 0);
    signal voltage_value     : std_logic_vector(SENSOR_WIDTH-1 downto 0);
    signal temperature_value : std_logic_vector(SENSOR_WIDTH-1 downto 0);
    signal current_threshold : std_logic_vector(SENSOR_WIDTH-1 downto 0);
    signal voltage_threshold : std_logic_vector(SENSOR_WIDTH-1 downto 0);
    signal temp_threshold    : std_logic_vector(SENSOR_WIDTH-1 downto 0);
    signal hysteresis        : std_logic_vector(SENSOR_WIDTH-1 downto 0);
    signal interlock_active  : std_logic;
    signal fault_current     : std_logic;
    signal fault_voltage     : std_logic;
    signal fault_temperature : std_logic;
    
    signal sim_done : boolean := false;
    
begin
    -- Instantiate interlock
    uut: entity work.interlock
        generic map (
            SENSOR_WIDTH => SENSOR_WIDTH
        )
        port map (
            clk               => clk,
            reset             => reset,
            current_value     => current_value,
            voltage_value     => voltage_value,
            temperature_value => temperature_value,
            current_threshold => current_threshold,
            voltage_threshold => voltage_threshold,
            temp_threshold    => temp_threshold,
            hysteresis        => hysteresis,
            interlock_active  => interlock_active,
            fault_current     => fault_current,
            fault_voltage     => fault_voltage,
            fault_temperature => fault_temperature
        );
    
    -- Clock generation
    clk_gen: process
    begin
        while not sim_done loop
            clk <= '0';
            wait for CLK_PERIOD/2;
            clk <= '1';
            wait for CLK_PERIOD/2;
        end loop;
        wait;
    end process;
    
    -- Stimulus
    stim: process
    begin
        -- Initialize
        reset <= '1';
        current_value     <= (others => '0');
        voltage_value     <= (others => '0');
        temperature_value <= (others => '0');
        
        -- Set thresholds
        current_threshold <= std_logic_vector(to_unsigned(3000, SENSOR_WIDTH)); -- Trip at 3000
        voltage_threshold <= std_logic_vector(to_unsigned(3500, SENSOR_WIDTH)); -- Trip at 3500
        temp_threshold    <= std_logic_vector(to_unsigned(2800, SENSOR_WIDTH)); -- Trip at 2800
        hysteresis        <= std_logic_vector(to_unsigned(200, SENSOR_WIDTH));  -- Clear 200 below trip
        
        wait for 50 ns;
        reset <= '0';
        wait for 50 ns;
        
        -- Test 1: Normal operation (all values below threshold)
        current_value     <= std_logic_vector(to_unsigned(2000, SENSOR_WIDTH));
        voltage_value     <= std_logic_vector(to_unsigned(2500, SENSOR_WIDTH));
        temperature_value <= std_logic_vector(to_unsigned(2000, SENSOR_WIDTH));
        wait for 100 ns;
        
        -- Test 2: Overcurrent trip
        current_value <= std_logic_vector(to_unsigned(3100, SENSOR_WIDTH)); -- Above 3000
        wait for 50 ns;
        
        -- Test 3: Reduce current but stay in hysteresis region
        current_value <= std_logic_vector(to_unsigned(2900, SENSOR_WIDTH)); -- Between 2800-3000
        wait for 50 ns;  -- Should still be in fault
        
        -- Test 4: Clear the fault (below clear threshold)
        current_value <= std_logic_vector(to_unsigned(2700, SENSOR_WIDTH)); -- Below 2800
        wait for 50 ns;
        
        -- Test 5: Overvoltage trip
        voltage_value <= std_logic_vector(to_unsigned(3600, SENSOR_WIDTH)); -- Above 3500
        wait for 50 ns;
        
        -- Test 6: Clear voltage
        voltage_value <= std_logic_vector(to_unsigned(3200, SENSOR_WIDTH)); -- Below 3300
        wait for 50 ns;
        
        -- Test 7: Overtemperature trip
        temperature_value <= std_logic_vector(to_unsigned(2900, SENSOR_WIDTH)); -- Above 2800
        wait for 50 ns;
        
        -- Test 8: Multiple faults simultaneously
        current_value     <= std_logic_vector(to_unsigned(3200, SENSOR_WIDTH));
        voltage_value     <= std_logic_vector(to_unsigned(3700, SENSOR_WIDTH));
        temperature_value <= std_logic_vector(to_unsigned(3000, SENSOR_WIDTH));
        wait for 100 ns;
        
        -- Test 9: Clear all faults
        current_value     <= std_logic_vector(to_unsigned(2000, SENSOR_WIDTH));
        voltage_value     <= std_logic_vector(to_unsigned(2500, SENSOR_WIDTH));
        temperature_value <= std_logic_vector(to_unsigned(2000, SENSOR_WIDTH));
        wait for 100 ns;
        
        -- End simulation
        sim_done <= true;
        wait;
    end process;
    
end architecture sim;

sim/interlock.vcd
$date
  Thu Jan 29 13:39:59 2026
$end
$version
  GHDL v0
$end
$timescale
  1 fs
$end
$scope module standard $end
$upscope $end
$scope module std_logic_1164 $end
$upscope $end
$scope module numeric_std $end
$upscope $end
$scope module interlock_tb $end
$var reg 1 ! clk $end
$var reg 1 " reset $end
$var reg 12 # current_value[11:0] $end
$var reg 12 $ voltage_value[11:0] $end
$var reg 12 % temperature_value[11:0] $end
$var reg 12 & current_threshold[11:0] $end
$var reg 12 ' voltage_threshold[11:0] $end
$var reg 12 ( temp_threshold[11:0] $end
$var reg 12 ) hysteresis[11:0] $end
$var reg 1 * interlock_active $end
$var reg 1 + fault_current $end
$var reg 1 , fault_voltage $end
$var reg 1 - fault_temperature $end
$var reg 1 . sim_done $end
$scope module uut $end
$var reg 1 / clk $end
$var reg 1 0 reset $end
$var reg 12 1 current_value[11:0] $end
$var reg 12 2 voltage_value[11:0] $end
$var reg 12 3 temperature_value[11:0] $end
$var reg 12 4 current_threshold[11:0] $end
$var reg 12 5 voltage_threshold[11:0] $end
$var reg 12 6 temp_threshold[11:0] $end
$var reg 12 7 hysteresis[11:0] $end
$var reg 1 8 interlock_active $end
$var reg 1 9 fault_current $end
$var reg 1 : fault_voltage $end
$var reg 1 ; fault_temperature $end
$var reg 12 < current_u[11:0] $end
$var reg 12 = voltage_u[11:0] $end
$var reg 12 > temperature_u[11:0] $end
$var reg 12 ? current_thresh_u[11:0] $end
$var reg 12 @ voltage_thresh_u[11:0] $end
$var reg 12 A temp_thresh_u[11:0] $end
$var reg 12 B hysteresis_u[11:0] $end
$var reg 1 C fault_current_int $end
$var reg 1 D fault_voltage_int $end
$var reg 1 E fault_temperature_int $end
$upscope $end
$upscope $end
$enddefinitions $end
#0
0!
1"
b000000000000 #
b000000000000 $
b000000000000 %
b101110111000 &
b110110101100 '
b101011110000 (
b000011001000 )
0*
0+
0,
0-
0.
0/
10
b000000000000 1
b000000000000 2
b000000000000 3
b101110111000 4
b110110101100 5
b101011110000 6
b000011001000 7
08
09
0:
0;
b000000000000 <
b000000000000 =
b000000000000 >
b101110111000 ?
b110110101100 @
b101011110000 A
b000011001000 B
0C
0D
0E
#5000000
1!
1/
#10000000
0!
0/
#15000000
1!
1/
#20000000
0!
0/
#25000000
1!
1/
#30000000
0!
0/
#35000000
1!
1/
#40000000
0!
0/
#45000000
1!
1/
#50000000
0!
0"
0/
00
#55000000
1!
1/
#60000000
0!
0/
#65000000
1!
1/
#70000000
0!
0/
#75000000
1!
1/
#80000000
0!
0/
#85000000
1!
1/
#90000000
0!
0/
#95000000
1!
1/
#100000000
0!
b011111010000 #
b100111000100 $
b011111010000 %
0/
b011111010000 1
b100111000100 2
b011111010000 3
b011111010000 <
b100111000100 =
b011111010000 >
#105000000
1!
1/
#110000000
0!
0/
#115000000
1!
1/
#120000000
0!
0/
#125000000
1!
1/
#130000000
0!
0/
#135000000
1!
1/
#140000000
0!
0/
#145000000
1!
1/
#150000000
0!
0/
#155000000
1!
1/
#160000000
0!
0/
#165000000
1!
1/
#170000000
0!
0/
#175000000
1!
1/
#180000000
0!
0/
#185000000
1!
1/
#190000000
0!
0/
#195000000
1!
1/
#200000000
0!
b110000011100 #
0/
b110000011100 1
b110000011100 <
#205000000
1!
1*
1+
1/
18
19
1C
#210000000
0!
0/
#215000000
1!
1/
#220000000
0!
0/
#225000000
1!
1/
#230000000
0!
0/
#235000000
1!
1/
#240000000
0!
0/
#245000000
1!
1/
#250000000
0!
b101101010100 #
0/
b101101010100 1
b101101010100 <
#255000000
1!
1/
#260000000
0!
0/
#265000000
1!
1/
#270000000
0!
0/
#275000000
1!
1/
#280000000
0!
0/
#285000000
1!
1/
#290000000
0!
0/
#295000000
1!
1/
#300000000
0!
b101010001100 #
0/
b101010001100 1
b101010001100 <
#305000000
1!
0*
0+
1/
08
09
0C
#310000000
0!
0/
#315000000
1!
1/
#320000000
0!
0/
#325000000
1!
1/
#330000000
0!
0/
#335000000
1!
1/
#340000000
0!
0/
#345000000
1!
1/
#350000000
0!
b111000010000 $
0/
b111000010000 2
b111000010000 =
#355000000
1!
1*
1,
1/
18
1:
1D
#360000000
0!
0/
#365000000
1!
1/
#370000000
0!
0/
#375000000
1!
1/
#380000000
0!
0/
#385000000
1!
1/
#390000000
0!
0/
#395000000
1!
1/
#400000000
0!
b110010000000 $
0/
b110010000000 2
b110010000000 =
#405000000
1!
0*
0,
1/
08
0:
0D
#410000000
0!
0/
#415000000
1!
1/
#420000000
0!
0/
#425000000
1!
1/
#430000000
0!
0/
#435000000
1!
1/
#440000000
0!
0/
#445000000
1!
1/
#450000000
0!
b101101010100 %
0/
b101101010100 3
b101101010100 >
#455000000
1!
1*
1-
1/
18
1;
1E
#460000000
0!
0/
#465000000
1!
1/
#470000000
0!
0/
#475000000
1!
1/
#480000000
0!
0/
#485000000
1!
1/
#490000000
0!
0/
#495000000
1!
1/
#500000000
0!
b110010000000 #
b111001110100 $
b101110111000 %
0/
b110010000000 1
b111001110100 2
b101110111000 3
b110010000000 <
b111001110100 =
b101110111000 >
#505000000
1!
1+
1,
1/
19
1:
1C
1D
#510000000
0!
0/
#515000000
1!
1/
#520000000
0!
0/
#525000000
1!
1/
#530000000
0!
0/
#535000000
1!
1/
#540000000
0!
0/
#545000000
1!
1/
#550000000
0!
0/
#555000000
1!
1/
#560000000
0!
0/
#565000000
1!
1/
#570000000
0!
0/
#575000000
1!
1/
#580000000
0!
0/
#585000000
1!
1/
#590000000
0!
0/
#595000000
1!
1/
#600000000
0!
b011111010000 #
b100111000100 $
b011111010000 %
0/
b011111010000 1
b100111000100 2
b011111010000 3
b011111010000 <
b100111000100 =
b011111010000 >
#605000000
1!
0*
0+
0,
0-
1/
08
09
0:
0;
0C
0D
0E
#610000000
0!
0/
#615000000
1!
1/
#620000000
0!
0/
#625000000
1!
1/
#630000000
0!
0/
#635000000
1!
1/
#640000000
0!
0/
#645000000
1!
1/
#650000000
0!
0/
#655000000
1!
1/
#660000000
0!
0/
#665000000
1!
1/
#670000000
0!
0/
#675000000
1!
1/
#680000000
0!
0/
#685000000
1!
1/
#690000000
0!
0/
#695000000
1!
1/
#700000000
0!
1.
0/
