rtl/pwm_generator.vhdl
library ieee;
use ieee.std_logic_1164.all;
use ieee.numeric_std.all;

entity pwm_generator is
    generic (
        COUNTER_WIDTH : integer := 8  -- 8 bits = 0 to 255
    );
    port (
        clk        : in  std_logic;
        reset      : in  std_logic;
        enable     : in  std_logic;
        duty_cycle : in  std_logic_vector(COUNTER_WIDTH-1 downto 0);
        pwm_out    : out std_logic
    );
end entity pwm_generator;

architecture rtl of pwm_generator is
    signal counter : unsigned(COUNTER_WIDTH-1 downto 0);
    signal duty_unsigned : unsigned(COUNTER_WIDTH-1 downto 0);
begin
    -- Convert duty_cycle input to unsigned for comparison
    duty_unsigned <= unsigned(duty_cycle);
    
    -- PWM counter process
    process(clk, reset)
    begin
        if reset = '1' then
            counter <= (others => '0');
            pwm_out <= '0';
        elsif rising_edge(clk) then
            if enable = '1' then
                -- Increment counter (wraps automatically)
                counter <= counter + 1;
                
                -- Compare and generate PWM output
                if counter < duty_unsigned then
                    pwm_out <= '1';
                else
                    pwm_out <= '0';
                end if;
            else
                -- When disabled, keep counter at 0 and output low
                counter <= (others => '0');
                pwm_out <= '0';
            end if;
        end if;
    end process;
    
end architecture rtl;

tb/pwm_generator_tb.vhdl
library ieee;
use ieee.std_logic_1164.all;
use ieee.numeric_std.all;

entity pwm_generator_tb is
end entity pwm_generator_tb;

architecture sim of pwm_generator_tb is
    constant CLK_PERIOD : time := 10 ns;
    constant COUNTER_WIDTH : integer := 8;
    
    signal clk        : std_logic := '0';
    signal reset      : std_logic := '0';
    signal enable     : std_logic := '0';
    signal duty_cycle : std_logic_vector(COUNTER_WIDTH-1 downto 0);
    signal pwm_out    : std_logic;
    
    signal sim_done : boolean := false;
    
begin
    -- Instantiate PWM generator
    uut: entity work.pwm_generator
        generic map (
            COUNTER_WIDTH => COUNTER_WIDTH
        )
        port map (
            clk        => clk,
            reset      => reset,
            enable     => enable,
            duty_cycle => duty_cycle,
            pwm_out    => pwm_out
        );
    
    -- Clock generation
    clk_gen: process
    begin
        while not sim_done loop
            clk <= '0';
            wait for CLK_PERIOD/2;
            clk <= '1';
            wait for CLK_PERIOD/2;
        end loop;
        wait;
    end process;
    
    -- Stimulus
    stim: process
    begin
        -- Reset
        reset <= '1';
        enable <= '0';
        duty_cycle <= (others => '0');
        wait for 50 ns;
        
        reset <= '0';
        wait for 20 ns;
        
        -- Test 1: 25% duty cycle
        duty_cycle <= std_logic_vector(to_unsigned(64, COUNTER_WIDTH)); -- 64/256 = 25%
        enable <= '1';
        wait for 3000 ns;  -- Wait for multiple PWM periods
        
        -- Test 2: 50% duty cycle
        duty_cycle <= std_logic_vector(to_unsigned(128, COUNTER_WIDTH)); -- 128/256 = 50%
        wait for 3000 ns;
        
        -- Test 3: 75% duty cycle
        duty_cycle <= std_logic_vector(to_unsigned(192, COUNTER_WIDTH)); -- 192/256 = 75%
        wait for 3000 ns;
        
        -- Test 4: 10% duty cycle
        duty_cycle <= std_logic_vector(to_unsigned(26, COUNTER_WIDTH)); -- 26/256 ≈ 10%
        wait for 3000 ns;
        
        -- Test 5: Disable PWM
        enable <= '0';
        wait for 500 ns;
        
        -- Test 6: Re-enable
        enable <= '1';
        wait for 2000 ns;
        
        -- End simulation
        sim_done <= true;
        wait;
    end process;
    
end architecture sim;

sim/pwm.vcd
$date
  Thu Jan 29 13:39:59 2026
$end
$version
  GHDL v0
$end
$timescale
  1 fs
$end
$scope module standard $end
$upscope $end
$scope module std_logic_1164 $end
$upscope $end
$scope module numeric_std $end
$upscope $end
$scope module pwm_generator_tb $end
$var reg 1 ! clk $end
$var reg 1 " reset $end
$var reg 1 # enable $end
$var reg 8 $ duty_cycle[7:0] $end
$var reg 1 % pwm_out $end
$var reg 1 & sim_done $end
$scope module uut $end
$var reg 1 ' clk $end
$var reg 1 ( reset $end
$var reg 1 ) enable $end
$var reg 8 * duty_cycle[7:0] $end
$var reg 1 + pwm_out $end
$var reg 8 , counter[7:0] $end
$var reg 8 - duty_unsigned[7:0] $end
$upscope $end
$upscope $end
$enddefinitions $end
#0
0!
1"
0#
b00000000 $
0%
0&
0'
1(
0)
b00000000 *
0+
b00000000 ,
b00000000 -
#5000000
1!
1'
#10000000
0!
0'
#15000000
1!
1'
#20000000
0!
0'
#25000000
1!
1'
#30000000
0!
0'
#35000000
1!
1'
#40000000
0!
0'
#45000000
1!
1'
#50000000
0!
0"
0'
0(
#55000000
1!
1'
#60000000
0!
0'
#65000000
1!
1'
#70000000
0!
1#
b01000000 $
0'
1)
b01000000 *
b01000000 -
#75000000
1!
1%
1'
1+
b00000001 ,
#80000000
0!
0'
#85000000
1!
1'
b00000010 ,
#90000000
0!
0'
#95000000
1!
1'
b00000011 ,
#100000000
0!
0'
#105000000
1!
1'
b00000100 ,
#110000000
0!
0'
#115000000
1!
1'
b00000101 ,
#120000000
0!
0'
#125000000
1!
1'
b00000110 ,
#130000000
0!
0'
#135000000
1!
1'
b00000111 ,
#140000000
0!
0'
#145000000
1!
1'
b00001000 ,
#150000000
0!
0'
#155000000
1!
1'
b00001001 ,
#160000000
0!
0'
#165000000
1!
1'
b00001010 ,
#170000000
0!
0'
#175000000
1!
1'
b00001011 ,
#180000000
0!
0'
#185000000
1!
1'
b00001100 ,
#190000000
0!
0'
#195000000
1!
1'
b00001101 ,
#200000000
0!
0'
#205000000
1!
1'
b00001110 ,
#210000000
0!
0'
#215000000
1!
1'
b00001111 ,
#220000000
0!
0'
#225000000
1!
1'
b00010000 ,
#230000000
0!
0'
#235000000
1!
1'
b00010001 ,
#240000000
0!
0'
#245000000
1!
1'
b00010010 ,
#250000000
0!
0'
#255000000
1!
1'
b00010011 ,
#260000000
0!
0'
#265000000
1!
1'
b00010100 ,
#270000000
0!
0'
#275000000
1!
1'
b00010101 ,
#280000000
0!
0'
#285000000
1!
1'
b00010110 ,
#290000000
0!
0'
#295000000
1!
1'
b00010111 ,
#300000000
0!
0'
#305000000
1!
1'
b00011000 ,
#310000000
0!
0'
#315000000
1!
1'
b00011001 ,
#320000000
0!
0'
#325000000
1!
1'
b00011010 ,
#330000000
0!
0'
#335000000
1!
1'
b00011011 ,
#340000000
0!
0'
#345000000
1!
1'
b00011100 ,
#350000000
0!
0'
#355000000
1!
1'
b00011101 ,
#360000000
0!
0'
#365000000
1!
1'
b00011110 ,
#370000000
0!
0'
#375000000
1!
1'
b00011111 ,
#380000000
0!
0'
#385000000
1!
1'
b00100000 ,
#390000000
0!
0'
#395000000
1!
1'
b00100001 ,
#400000000
0!
0'
#405000000
1!
1'
b00100010 ,
#410000000
0!
0'
#415000000
1!
1'
b00100011 ,
#420000000
0!
0'
#425000000
1!
1'
b00100100 ,
#430000000
0!
0'
#435000000
1!
1'
b00100101 ,
#440000000
0!
0'
#445000000
1!
1'
b00100110 ,
#450000000
0!
0'
#455000000
1!
1'
b00100111 ,
#460000000
0!
0'
#465000000
1!
1'
b00101000 ,
#470000000
0!
0'
#475000000
1!
1'
b00101001 ,
#480000000
0!
0'
#485000000
1!
1'
b00101010 ,
#490000000
0!
0'
#495000000
1!
1'
b00101011 ,
#500000000
0!
0'
#505000000
1!
1'
b00101100 ,
#510000000
0!
0'
#515000000
1!
1'
b00101101 ,
#520000000
0!
0'
#525000000
1!
1'
b00101110 ,
#530000000
0!
0'
#535000000
1!
1'
b00101111 ,
#540000000
0!
0'
#545000000
1!
1'
b00110000 ,
#550000000
0!
0'
#555000000
1!
1'
b00110001 ,
#560000000
0!
0'
#565000000
1!
1'
b00110010 ,
#570000000
0!
0'
#575000000
1!
1'
b00110011 ,
#580000000
0!
0'
#585000000
1!
1'
b00110100 ,
#590000000
0!
0'
#595000000
1!
1'
b00110101 ,
#600000000
0!
0'
#605000000
1!
1'
b00110110 ,
#610000000
0!
0'
#615000000
1!
1'
b00110111 ,
#620000000
0!
0'
#625000000
1!
1'
b00111000 ,
#630000000
0!
0'
#635000000
1!
1'
b00111001 ,
#640000000
0!
0'
#645000000
1!
1'
b00111010 ,
#650000000
0!
0'
#655000000
1!
1'
b00111011 ,
#660000000
0!
0'
#665000000
1!
1'
b00111100 ,
#670000000
0!
0'
#675000000
1!
1'
b00111101 ,
#680000000
0!
0'
#685000000
1!
1'
b00111110 ,
#690000000
0!
0'
#695000000
1!
1'
b00111111 ,
#700000000
0!
0'
#705000000
1!
1'
b01000000 ,
#710000000
0!
0'
#715000000
1!
0%
1'
0+
b01000001 ,
#720000000
0!
0'
#725000000
1!
1'
b01000010 ,
#730000000
0!
0'
#735000000
1!
1'
b01000011 ,
#740000000
0!
0'
#745000000
1!
1'
b01000100 ,
#750000000
0!
0'
#755000000
1!
1'
b01000101 ,
#760000000
0!
0'
#765000000
1!
1'
b01000110 ,
#770000000
0!
0'
#775000000
1!
1'
b01000111 ,
#780000000
0!
0'
#785000000
1!
1'
b01001000 ,
#790000000
0!
0'
#795000000
1!
1'
b01001001 ,
#800000000
0!
0'
#805000000
1!
1'
b01001010 ,
#810000000
0!
0'
#815000000
1!
1'
b01001011 ,
#820000000
0!
0'
#825000000
1!
1'
b01001100 ,
#830000000
0!
0'
#835000000
1!
1'
b01001101 ,
#840000000
0!
0'
#845000000
1!
1'
b01001110 ,
#850000000
0!
0'
#855000000
1!
1'
b01001111 ,
#860000000
0!
0'
#865000000
1!
1'
b01010000 ,
#870000000
0!
0'
#875000000
1!
1'
b01010001 ,
#880000000
0!
0'
#885000000
1!
1'
b01010010 ,
#890000000
0!
0'
#895000000
1!
1'
b01010011 ,
#900000000
0!
0'
#905000000
1!
1'
b01010100 ,
#910000000
0!
0'
#915000000
1!
1'
b01010101 ,
#920000000
0!
0'
#925000000
1!
1'
b01010110 ,
#930000000
0!
0'
#935000000
1!
1'
b01010111 ,
#940000000
0!
0'
#945000000
1!
1'
b01011000 ,
#950000000
0!
0'
#955000000
1!
1'
b01011001 ,
#960000000
0!
0'
#965000000
1!
1'
b01011010 ,
#970000000
0!
0'
#975000000
1!
1'
b01011011 ,
#980000000
0!
0'
#985000000
1!
1'
b01011100 ,
#990000000
0!
0'
#995000000
1!
1'
b01011101 ,
#1000000000
0!
0'
#1005000000
1!
1'
b01011110 ,
#1010000000
0!
0'
#1015000000
1!
1'
b01011111 ,
#1020000000
0!
0'
#1025000000
1!
1'
b01100000 ,
#1030000000
0!
0'
#1035000000
1!
1'
b01100001 ,
#1040000000
0!
0'
#1045000000
1!
1'
b01100010 ,
#1050000000
0!
0'
#1055000000
1!
1'
b01100011 ,
#1060000000
0!
0'
#1065000000
1!
1'
b01100100 ,
#1070000000
0!
0'
#1075000000
1!
1'
b01100101 ,
#1080000000
0!
0'
#1085000000
1!
1'
b01100110 ,
#1090000000
0!
0'
#1095000000
1!
1'
b01100111 ,
#1100000000
0!
0'
#1105000000
1!
1'
b01101000 ,
#1110000000
0!
0'
#1115000000
1!
1'
b01101001 ,
#1120000000
0!
0'
#1125000000
1!
1'
b01101010 ,
#1130000000
0!
0'
#1135000000
1!
1'
b01101011 ,
#1140000000
0!
0'
#1145000000
1!
1'
b01101100 ,
#1150000000
0!
0'
#1155000000
1!
1'
b01101101 ,
#1160000000
0!
0'
#1165000000
1!
1'
b01101110 ,
#1170000000
0!
0'
#1175000000
1!
1'
b01101111 ,
#1180000000
0!
0'
#1185000000
1!
1'
b01110000 ,
#1190000000
0!
0'
#1195000000
1!
1'
b01110001 ,
#1200000000
0!
0'
#1205000000
1!
1'
b01110010 ,
#1210000000
0!
0'
#1215000000
1!
1'
b01110011 ,
#1220000000
0!
0'
#1225000000
1!
1'
b01110100 ,
#1230000000
0!
0'
#1235000000
1!
1'
b01110101 ,
#1240000000
0!
0'
#1245000000
1!
1'
b01110110 ,
#1250000000
0!
0'
#1255000000
1!
1'
b01110111 ,
#1260000000
0!
0'
#1265000000
1!
1'
b01111000 ,
#1270000000
0!
0'
#1275000000
1!
1'
b01111001 ,
#1280000000
0!
0'
#1285000000
1!
1'
b01111010 ,
#1290000000
0!
0'
#1295000000
1!
1'
b01111011 ,
#1300000000
0!
0'
#1305000000
1!
1'
b01111100 ,
#1310000000
0!
0'
#1315000000
1!
1'
b01111101 ,
#1320000000
0!
0'
#1325000000
1!
1'
b01111110 ,
#1330000000
0!
0'
#1335000000
1!
1'
b01111111 ,
#1340000000
0!
0'
#1345000000
1!
1'
b10000000 ,
#1350000000
0!
0'
#1355000000
1!
1'
b10000001 ,
#1360000000
0!
0'
#1365000000
1!
1'
b10000010 ,
#1370000000
0!
0'
#1375000000
1!
1'
b10000011 ,
#1380000000
0!
0'
#1385000000
1!
1'
b10000100 ,
#1390000000
0!
0'
#1395000000
1!
1'
b10000101 ,
#1400000000
0!
0'
#1405000000
1!
1'
b10000110 ,
#1410000000
0!
0'
#1415000000
1!
1'
b10000111 ,
#1420000000
0!
0'
#1425000000
1!
1'
b10001000 ,
#1430000000
0!
0'
#1435000000
1!
1'
b10001001 ,
#1440000000
0!
0'
#1445000000
1!
1'
b10001010 ,
#1450000000
0!
0'
#1455000000
1!
1'
b10001011 ,
#1460000000
0!
0'
#1465000000
1!
1'
b10001100 ,
#1470000000
0!
0'
#1475000000
1!
1'
b10001101 ,
#1480000000
0!
0'
#1485000000
1!
1'
b10001110 ,
#1490000000
0!
0'
#1495000000
1!
1'
b10001111 ,
#1500000000
0!
0'
#1505000000
1!
1'
b10010000 ,
#1510000000
0!
0'
#1515000000
1!
1'
b10010001 ,
#1520000000
0!
0'
#1525000000
1!
1'
b10010010 ,
#1530000000
0!
0'
#1535000000
1!
1'
b10010011 ,
#1540000000
0!
0'
#1545000000
1!
1'
b10010100 ,
#1550000000
0!
0'
#1555000000
1!
1'
b10010101 ,
#1560000000
0!
0'
#1565000000
1!
1'
b10010110 ,
#1570000000
0!
0'
#1575000000
1!
1'
b10010111 ,
#1580000000
0!
0'
#1585000000
1!
1'
b10011000 ,
#1590000000
0!
0'
#1595000000
1!
1'
b10011001 ,
#1600000000
0!
0'
#1605000000
1!
1'
b10011010 ,
#1610000000
0!
0'
#1615000000
1!
1'
b10011011 ,
#1620000000
0!
0'
#1625000000
1!
1'
b10011100 ,
#1630000000
0!
0'
#1635000000
1!
1'
b10011101 ,
#1640000000
0!
0'
#1645000000
1!
1'
b10011110 ,
#1650000000
0!
0'
#1655000000
1!
1'
b10011111 ,
#1660000000
0!
0'
#1665000000
1!
1'
b10100000 ,
#1670000000
0!
0'
#1675000000
1!
1'
b10100001 ,
#1680000000
0!
0'
#1685000000
1!
1'
b10100010 ,
#1690000000
0!
0'
#1695000000
1!
1'
b10100011 ,
#1700000000
0!
0'
#1705000000
1!
1'
b10100100 ,
#1710000000
0!
0'
#1715000000
1!
1'
b10100101 ,
#1720000000
0!
0'
#1725000000
1!
1'
b10100110 ,
#1730000000
0!
0'
#1735000000
1!
1'
b10100111 ,
#1740000000
0!
0'
#1745000000
1!
1'
b10101000 ,
#1750000000
0!
0'
#1755000000
1!
1'
b10101001 ,
#1760000000
0!
0'
#1765000000
1!
1'
b10101010 ,
#1770000000
0!
0'
#1775000000
1!
1'
b10101011 ,
#1780000000
0!
0'
#1785000000
1!
1'
b10101100 ,
#1790000000
0!
0'
#1795000000
1!
1'
b10101101 ,
#1800000000
0!
0'
#1805000000
1!
1'
b10101110 ,
#1810000000
0!
0'
#1815000000
1!
1'
b10101111 ,
#1820000000
0!
0'
#1825000000
1!
1'
b10110000 ,
#1830000000
0!
0'
#1835000000
1!
1'
b10110001 ,
#1840000000
0!
0'
#1845000000
1!
1'
b10110010 ,
#1850000000
0!
0'
#1855000000
1!
1'
b10110011 ,
#1860000000
0!
0'
#1865000000
1!
1'
b10110100 ,
#1870000000
0!
0'
#1875000000
1!
1'
b10110101 ,
#1880000000
0!
0'
#1885000000
1!
1'
b10110110 ,
#1890000000
0!
0'
#1895000000
1!
1'
b10110111 ,
#1900000000
0!
0'
#1905000000
1!
1'
b10111000 ,
#1910000000
0!
0'
#1915000000
1!
1'
b10111001 ,
#1920000000
0!
0'
#1925000000
1!
1'
b10111010 ,
#1930000000
0!
0'
#1935000000
1!
1'
b10111011 ,
#1940000000
0!
0'
#1945000000
1!
1'
b10111100 ,
#1950000000
0!
0'
#1955000000
1!
1'
b10111101 ,
#1960000000
0!
0'
#1965000000
1!
1'
b10111110 ,
#1970000000
0!
0'
#1975000000
1!
1'
b10111111 ,
#1980000000
0!
0'
#1985000000
1!
1'
b11000000 ,
#1990000000
0!
0'
#1995000000
1!
1'
b11000001 ,
#2000000000
0!
0'
#2005000000
1!
1'
b11000010 ,
#2010000000
0!
0'
#2015000000
1!
1'
b11000011 ,
#2020000000
0!
0'
#2025000000
1!
1'
b11000100 ,
#2030000000
0!
0'
#2035000000
1!
1'
b11000101 ,
#2040000000
0!
0'
#2045000000
1!
1'
b11000110 ,
#2050000000
0!
0'
#2055000000
1!
1'
b11000111 ,
#2060000000
0!
0'
#2065000000
1!
1'
b11001000 ,
#2070000000
0!
0'
#2075000000
1!
1'
b11001001 ,
#2080000000
0!
0'
#2085000000
1!
1'
b11001010 ,
#2090000000
0!
0'
#2095000000
1!
1'
b11001011 ,
#2100000000
0!
0'
#2105000000
1!
1'
b11001100 ,
#2110000000
0!
0'
#2115000000
1!
1'
b11001101 ,
#2120000000
0!
0'
#2125000000
1!
1'
b11001110 ,
#2130000000
0!
0'
#2135000000
1!
1'
b11001111 ,
#2140000000
0!
0'
#2145000000
1!
1'
b11010000 ,
#2150000000
0!
0'
#2155000000
1!
1'
b11010001 ,
#2160000000
0!
0'
#2165000000
1!
1'
b11010010 ,
#2170000000
0!
0'
#2175000000
1!
1'
b11010011 ,
#2180000000
0!
0'
#2185000000
1!
1'
b11010100 ,
#2190000000
0!
0'
#2195000000
1!
1'
b11010101 ,
#2200000000
0!
0'
#2205000000
1!
1'
b11010110 ,
#2210000000
0!
0'
#2215000000
1!
1'
b11010111 ,
#2220000000
0!
0'
#2225000000
1!
1'
b11011000 ,
#2230000000
0!
0'
#2235000000
1!
1'
b11011001 ,
#2240000000
0!
0'
#2245000000
1!
1'
b11011010 ,
#2250000000
0!
0'
#2255000000
1!
1'
b11011011 ,
#2260000000
0!
0'
#2265000000
1!
1'
b11011100 ,
#2270000000
0!
0'
#2275000000
1!
1'
b11011101 ,
#2280000000
0!
0'
#2285000000
1!
1'
b11011110 ,
#2290000000
0!
0'
#2295000000
1!
1'
b11011111 ,
#2300000000
0!
0'
#2305000000
1!
1'
b11100000 ,
#2310000000
0!
0'
#2315000000
1!
1'
b11100001 ,
#2320000000
0!
0'
#2325000000
1!
1'
b11100010 ,
#2330000000
0!
0'
#2335000000
1!
1'
b11100011 ,
#2340000000
0!
0'
#2345000000
1!
1'
b11100100 ,
#2350000000
0!
0'
#2355000000
1!
1'
b11100101 ,
#2360000000
0!
0'
#2365000000
1!
1'
b11100110 ,
#2370000000
0!
0'
#2375000000
1!
1'
b11100111 ,
#2380000000
0!
0'
#2385000000
1!
1'
b11101000 ,
#2390000000
0!
0'
#2395000000
1!
1'
b11101001 ,
#2400000000
0!
0'
#2405000000
1!
1'
b11101010 ,
#2410000000
0!
0'
#2415000000
1!
1'
b11101011 ,
#2420000000
0!
0'
#2425000000
1!
1'
b11101100 ,
#2430000000
0!
0'
#2435000000
1!
1'
b11101101 ,
#2440000000
0!
0'
#2445000000
1!
1'
b11101110 ,
#2450000000
0!
0'
#2455000000
1!
1'
b11101111 ,
#2460000000
0!
0'
#2465000000
1!
1'
b11110000 ,
#2470000000
0!
0'
#2475000000
1!
1'
b11110001 ,
#2480000000
0!
0'
#2485000000
1!
1'
b11110010 ,
#2490000000
0!
0'
#2495000000
1!
1'
b11110011 ,
#2500000000
0!
0'
#2505000000
1!
1'
b11110100 ,
#2510000000
0!
0'
#2515000000
1!
1'
b11110101 ,
#2520000000
0!
0'
#2525000000
1!
1'
b11110110 ,
#2530000000
0!
0'
#2535000000
1!
1'
b11110111 ,
#2540000000
0!
0'
#2545000000
1!
1'
b11111000 ,
#2550000000
0!
0'
#2555000000
1!
1'
b11111001 ,
#2560000000
0!
0'
#2565000000
1!
1'
b11111010 ,
#2570000000
0!
0'
#2575000000
1!
1'
b11111011 ,
#2580000000
0!
0'
#2585000000
1!
1'
b11111100 ,
#2590000000
0!
0'
#2595000000
1!
1'
b11111101 ,
#2600000000
0!
0'
#2605000000
1!
1'
b11111110 ,
#2610000000
0!
0'
#2615000000
1!
1'
b11111111 ,
#2620000000
0!
0'
#2625000000
1!
1'
b00000000 ,
#2630000000
0!
0'
#2635000000
1!
1%
1'
1+
b00000001 ,
#2640000000
0!
0'
#2645000000
1!
1'
b00000010 ,
#2650000000
0!
0'
#2655000000
1!
1'
b00000011 ,
#2660000000
0!
0'
#2665000000
1!
1'
b00000100 ,
#2670000000
0!
0'
#2675000000
1!
1'
b00000101 ,
#2680000000
0!
0'
#2685000000
1!
1'
b00000110 ,
#2690000000
0!
0'
#2695000000
1!
1'
b00000111 ,
#2700000000
0!
0'
#2705000000
1!
1'
b00001000 ,
#2710000000
0!
0'
#2715000000
1!
1'
b00001001 ,
#2720000000
0!
0'
#2725000000
1!
1'
b00001010 ,
#2730000000
0!
0'
#2735000000
1!
1'
b00001011 ,
#2740000000
0!
0'
#2745000000
1!
1'
b00001100 ,
#2750000000
0!
0'
#2755000000
1!
1'
b00001101 ,
#2760000000
0!
0'
#2765000000
1!
1'
b00001110 ,
#2770000000
0!
0'
#2775000000
1!
1'
b00001111 ,
#2780000000
0!
0'
#2785000000
1!
1'
b00010000 ,
#2790000000
0!
0'
#2795000000
1!
1'
b00010001 ,
#2800000000
0!
0'
#2805000000
1!
1'
b00010010 ,
#2810000000
0!
0'
#2815000000
1!
1'
b00010011 ,
#2820000000
0!
0'
#2825000000
1!
1'
b00010100 ,
#2830000000
0!
0'
#2835000000
1!
1'
b00010101 ,
#2840000000
0!
0'
#2845000000
1!
1'
b00010110 ,
#2850000000
0!
0'
#2855000000
1!
1'
b00010111 ,
#2860000000
0!
0'
#2865000000
1!
1'
b00011000 ,
#2870000000
0!
0'
#2875000000
1!
1'
b00011001 ,
#2880000000
0!
0'
#2885000000
1!
1'
b00011010 ,
#2890000000
0!
0'
#2895000000
1!
1'
b00011011 ,
#2900000000
0!
0'
#2905000000
1!
1'
b00011100 ,
#2910000000
0!
0'
#2915000000
1!
1'
b00011101 ,
#2920000000
0!
0'
#2925000000
1!
1'
b00011110 ,
#2930000000
0!
0'
#2935000000
1!
1'
b00011111 ,
#2940000000
0!
0'
#2945000000
1!
1'
b00100000 ,
#2950000000
0!
0'
#2955000000
1!
1'
b00100001 ,
#2960000000
0!
0'
#2965000000
1!
1'
b00100010 ,
#2970000000
0!
0'
#2975000000
1!
1'
b00100011 ,
#2980000000
0!
0'
#2985000000
1!
1'
b00100100 ,
#2990000000
0!
0'
#2995000000
1!
1'
b00100101 ,
#3000000000
0!
0'
#3005000000
1!
1'
b00100110 ,
#3010000000
0!
0'
#3015000000
1!
1'
b00100111 ,
#3020000000
0!
0'
#3025000000
1!
1'
b00101000 ,
#3030000000
0!
0'
#3035000000
1!
1'
b00101001 ,
#3040000000
0!
0'
#3045000000
1!
1'
b00101010 ,
#3050000000
0!
0'
#3055000000
1!
1'
b00101011 ,
#3060000000
0!
0'
#3065000000
1!
1'
b00101100 ,
#3070000000
0!
b10000000 $
0'
b10000000 *
b10000000 -
#3075000000
1!
1'
b00101101 ,
#3080000000
0!
0'
#3085000000
1!
1'
b00101110 ,
#3090000000
0!
0'
#3095000000
1!
1'
b00101111 ,
#3100000000
0!
0'
#3105000000
1!
1'
b00110000 ,
#3110000000
0!
0'
#3115000000
1!
1'
b00110001 ,
#3120000000
0!
0'
#3125000000
1!
1'
b00110010 ,
#3130000000
0!
0'
#3135000000
1!
1'
b00110011 ,
#3140000000
0!
0'
#3145000000
1!
1'
b00110100 ,
#3150000000
0!
0'
#3155000000
1!
1'
b00110101 ,
#3160000000
0!
0'
#3165000000
1!
1'
b00110110 ,
#3170000000
0!
0'
#3175000000
1!
1'
b00110111 ,
#3180000000
0!
0'
#3185000000
1!
1'
b00111000 ,
#3190000000
0!
0'
#3195000000
1!
1'
b00111001 ,
#3200000000
0!
0'
#3205000000
1!
1'
b00111010 ,
#3210000000
0!
0'
#3215000000
1!
1'
b00111011 ,
#3220000000
0!
0'
#3225000000
1!
1'
b00111100 ,
#3230000000
0!
0'
#3235000000
1!
1'
b00111101 ,
#3240000000
0!
0'
#3245000000
1!
1'
b00111110 ,
#3250000000
0!
0'
#3255000000
1!
1'
b00111111 ,
#3260000000
0!
0'
#3265000000
1!
1'
b01000000 ,
#3270000000
0!
0'
#3275000000
1!
1'
b01000001 ,
#3280000000
0!
0'
#3285000000
1!
1'
b01000010 ,
#3290000000
0!
0'
#3295000000
1!
1'
b01000011 ,
#3300000000
0!
0'
#3305000000
1!
1'
b01000100 ,
#3310000000
0!
0'
#3315000000
1!
1'
b01000101 ,
#3320000000
0!
0'
#3325000000
1!
1'
b01000110 ,
#3330000000
0!
0'
#3335000000
1!
1'
b01000111 ,
#3340000000
0!
0'
#3345000000
1!
1'
b01001000 ,
#3350000000
0!
0'
#3355000000
1!
1'
b01001001 ,
#3360000000
0!
0'
#3365000000
1!
1'
b01001010 ,
#3370000000
0!
0'
#3375000000
1!
1'
b01001011 ,
#3380000000
0!
0'
#3385000000
1!
1'
b01001100 ,
#3390000000
0!
0'
#3395000000
1!
1'
b01001101 ,
#3400000000
0!
0'
#3405000000
1!
1'
b01001110 ,
#3410000000
0!
0'
#3415000000
1!
1'
b01001111 ,
#3420000000
0!
0'
#3425000000
1!
1'
b01010000 ,
#3430000000
0!
0'
#3435000000
1!
1'
b01010001 ,
#3440000000
0!
0'
#3445000000
1!
1'
b01010010 ,
#3450000000
0!
0'
#3455000000
1!
1'
b01010011 ,
#3460000000
0!
0'
#3465000000
1!
1'
b01010100 ,
#3470000000
0!
0'
#3475000000
1!
1'
b01010101 ,
#3480000000
0!
0'
#3485000000
1!
1'
b01010110 ,
#3490000000
0!
0'
#3495000000
1!
1'
b01010111 ,
#3500000000
0!
0'
#3505000000
1!
1'
b01011000 ,
#3510000000
0!
0'
#3515000000
1!
1'
b01011001 ,
#3520000000
0!
0'
#3525000000
1!
1'
b01011010 ,
#3530000000
0!
0'
#3535000000
1!
1'
b01011011 ,
#3540000000
0!
0'
#3545000000
1!
1'
b01011100 ,
#3550000000
0!
0'
#3555000000
1!
1'
b01011101 ,
#3560000000
0!
0'
#3565000000
1!
1'
b01011110 ,
#3570000000
0!
0'
#3575000000
1!
1'
b01011111 ,
#3580000000
0!
0'
#3585000000
1!
1'
b01100000 ,
#3590000000
0!
0'
#3595000000
1!
1'
b01100001 ,
#3600000000
0!
0'
#3605000000
1!
1'
b01100010 ,
#3610000000
0!
0'
#3615000000
1!
1'
b01100011 ,
#3620000000
0!
0'
#3625000000
1!
1'
b01100100 ,
#3630000000
0!
0'
#3635000000
1!
1'
b01100101 ,
#3640000000
0!
0'
#3645000000
1!
1'
b01100110 ,
#3650000000
0!
0'
#3655000000
1!
1'
b01100111 ,
#3660000000
0!
0'
#3665000000
1!
1'
b01101000 ,
#3670000000
0!
0'
#3675000000
1!
1'
b01101001 ,
#3680000000
0!
0'
#3685000000
1!
1'
b01101010 ,
#3690000000
0!
0'
#3695000000
1!
1'
b01101011 ,
#3700000000
0!
0'
#3705000000
1!
1'
b01101100 ,
#3710000000
0!
0'
#3715000000
1!
1'
b01101101 ,
#3720000000
0!
0'
#3725000000
1!
1'
b01101110 ,
#3730000000
0!
0'
#3735000000
1!
1'
b01101111 ,
#3740000000
0!
0'
#3745000000
1!
1'
b01110000 ,
#3750000000
0!
0'
#3755000000
1!
1'
b01110001 ,
#3760000000
0!
0'
#3765000000
1!
1'
b01110010 ,
#3770000000
0!
0'
#3775000000
1!
1'
b01110011 ,
#3780000000
0!
0'
#3785000000
1!
1'
b01110100 ,
#3790000000
0!
0'
#3795000000
1!
1'
b01110101 ,
#3800000000
0!
0'
#3805000000
1!
1'
b01110110 ,
#3810000000
0!
0'
#3815000000
1!
1'
b01110111 ,
#3820000000
0!
0'
#3825000000
1!
1'
b01111000 ,
#3830000000
0!
0'
#3835000000
1!
1'
b01111001 ,
#3840000000
0!
0'
#3845000000
1!
1'
b01111010 ,
#3850000000
0!
0'
#3855000000
1!
1'
b01111011 ,
#3860000000
0!
0'
#3865000000
1!
1'
b01111100 ,
#3870000000
0!
0'
#3875000000
1!
1'
b01111101 ,
#3880000000
0!
0'
#3885000000
1!
1'
b01111110 ,
#3890000000
0!
0'
#3895000000
1!
1'
b01111111 ,
#3900000000
0!
0'
#3905000000
1!
1'
b10000000 ,
#3910000000
0!
0'
#3915000000
1!
0%
1'
0+
b10000001 ,
#3920000000
0!
0'
#3925000000
1!
1'
b10000010 ,
#3930000000
0!
0'
#3935000000
1!
1'
b10000011 ,
#3940000000
0!
0'
#3945000000
1!
1'
b10000100 ,
#3950000000
0!
0'
#3955000000
1!
1'
b10000101 ,
#3960000000
0!
0'
#3965000000
1!
1'
b10000110 ,
#3970000000
0!
0'
#3975000000
1!
1'
b10000111 ,
#3980000000
0!
0'
#3985000000
1!
1'
b10001000 ,
#3990000000
0!
0'
#3995000000
1!
1'
b10001001 ,
#4000000000
0!
0'
#4005000000
1!
1'
b10001010 ,
#4010000000
0!
0'
#4015000000
1!
1'
b10001011 ,
#4020000000
0!
0'
#4025000000
1!
1'
b10001100 ,
#4030000000
0!
0'
#4035000000
1!
1'
b10001101 ,
#4040000000
0!
0'
#4045000000
1!
1'
b10001110 ,
#4050000000
0!
0'
#4055000000
1!
1'
b10001111 ,
#4060000000
0!
0'
#4065000000
1!
1'
b10010000 ,
#4070000000
0!
0'
#4075000000
1!
1'
b10010001 ,
#4080000000
0!
0'
#4085000000
1!
1'
b10010010 ,
