rtl/interlock.vhdl
library ieee;
use ieee.std_logic_1164.all;
use ieee.numeric_std.all;

entity interlock is
    generic (
        SENSOR_WIDTH : integer := 12  -- 12-bit ADC values (0-4095)
    );
    port (
        clk                : in  std_logic;
        reset              : in  std_logic;
        
        -- Sensor inputs (from ADCs measuring current, voltage, temp)
        current_value      : in  std_logic_vector(SENSOR_WIDTH-1 downto 0);
        voltage_value      : in  std_logic_vector(SENSOR_WIDTH-1 downto 0);
        temperature_value  : in  std_logic_vector(SENSOR_WIDTH-1 downto 0);
        
        -- Threshold settings
        current_threshold  : in  std_logic_vector(SENSOR_WIDTH-1 downto 0);
        voltage_threshold  : in  std_logic_vector(SENSOR_WIDTH-1 downto 0);
        temp_threshold     : in  std_logic_vector(SENSOR_WIDTH-1 downto 0);
        
        -- Hysteresis (threshold - hysteresis = clear level)
        hysteresis         : in  std_logic_vector(SENSOR_WIDTH-1 downto 0);
        
        -- Outputs
        interlock_active   : out std_logic;  -- '1' = fault detected, disable PWM
        fault_current      : out std_logic;  -- Which fault occurred
        fault_voltage      : out std_logic;
        fault_temperature  : out std_logic
    );
end entity interlock;

architecture rtl of interlock is
    -- Convert to unsigned for comparison
    signal current_u      : unsigned(SENSOR_WIDTH-1 downto 0);
    signal voltage_u      : unsigned(SENSOR_WIDTH-1 downto 0);
    signal temperature_u  : unsigned(SENSOR_WIDTH-1 downto 0);
    
    signal current_thresh_u  : unsigned(SENSOR_WIDTH-1 downto 0);
    signal voltage_thresh_u  : unsigned(SENSOR_WIDTH-1 downto 0);
    signal temp_thresh_u     : unsigned(SENSOR_WIDTH-1 downto 0);
    signal hysteresis_u      : unsigned(SENSOR_WIDTH-1 downto 0);
    
    -- Fault flags (internal)
    signal fault_current_int      : std_logic;
    signal fault_voltage_int      : std_logic;
    signal fault_temperature_int  : std_logic;
    
begin
    -- Type conversions
    current_u       <= unsigned(current_value);
    voltage_u       <= unsigned(voltage_value);
    temperature_u   <= unsigned(temperature_value);
    
    current_thresh_u  <= unsigned(current_threshold);
    voltage_thresh_u  <= unsigned(voltage_threshold);
    temp_thresh_u     <= unsigned(temp_threshold);
    hysteresis_u      <= unsigned(hysteresis);
    
    -- Main interlock logic with hysteresis
    process(clk, reset)
        variable clear_current_thresh  : unsigned(SENSOR_WIDTH-1 downto 0);
        variable clear_voltage_thresh  : unsigned(SENSOR_WIDTH-1 downto 0);
        variable clear_temp_thresh     : unsigned(SENSOR_WIDTH-1 downto 0);
    begin
        if reset = '1' then
            fault_current_int     <= '0';
            fault_voltage_int     <= '0';
            fault_temperature_int <= '0';
            
        elsif rising_edge(clk) then
            -- Calculate clear thresholds (trip - hysteresis)
            clear_current_thresh := current_thresh_u - hysteresis_u;
            clear_voltage_thresh := voltage_thresh_u - hysteresis_u;
            clear_temp_thresh    := temp_thresh_u - hysteresis_u;
            
            -- Current interlock with hysteresis
            if current_u >= current_thresh_u then
                fault_current_int <= '1';  -- Trip
            elsif current_u < clear_current_thresh then
                fault_current_int <= '0';  -- Clear
            end if;
            -- Otherwise maintain current state (hysteresis region)
            
            -- Voltage interlock with hysteresis
            if voltage_u >= voltage_thresh_u then
                fault_voltage_int <= '1';
            elsif voltage_u < clear_voltage_thresh then
                fault_voltage_int <= '0';
            end if;
            
            -- Temperature interlock with hysteresis
            if temperature_u >= temp_thresh_u then
                fault_temperature_int <= '1';
            elsif temperature_u < clear_temp_thresh then
                fault_temperature_int <= '0';
            end if;
        end if;
    end process;
    
    -- Output assignment (combinational for fastest response)
    interlock_active  <= fault_current_int or fault_voltage_int or fault_temperature_int;
    fault_current     <= fault_current_int;
    fault_voltage     <= fault_voltage_int;
    fault_temperature <= fault_temperature_int;
    
end architecture rtl;

rtl/pwm_generator.vhdl
library ieee;
use ieee.std_logic_1164.all;
use ieee.numeric_std.all;

entity pwm_generator is
    generic (
        COUNTER_WIDTH : integer := 8  -- 8 bits = 0 to 255
    );
    port (
        clk        : in  std_logic;
        reset      : in  std_logic;
        enable     : in  std_logic;
        duty_cycle : in  std_logic_vector(COUNTER_WIDTH-1 downto 0);
        pwm_out    : out std_logic
    );
end entity pwm_generator;

architecture rtl of pwm_generator is
    signal counter : unsigned(COUNTER_WIDTH-1 downto 0);
    signal duty_unsigned : unsigned(COUNTER_WIDTH-1 downto 0);
begin
    -- Convert duty_cycle input to unsigned for comparison
    duty_unsigned <= unsigned(duty_cycle);
    
    -- PWM counter process
    process(clk, reset)
    begin
        if reset = '1' then
            counter <= (others => '0');
            pwm_out <= '0';
        elsif rising_edge(clk) then
            if enable = '1' then
                -- Increment counter (wraps automatically)
                counter <= counter + 1;
                
                -- Compare and generate PWM output
                if counter < duty_unsigned then
                    pwm_out <= '1';
                else
                    pwm_out <= '0';
                end if;
            else
                -- When disabled, keep counter at 0 and output low
                counter <= (others => '0');
                pwm_out <= '0';
            end if;
        end if;
    end process;
    
end architecture rtl;

rtl/pwm_controller.vhdl
library ieee;
use ieee.std_logic_1164.all;
use ieee.numeric_std.all;

entity pwm_controller is
    generic (
        PWM_WIDTH    : integer := 8;   -- PWM resolution
        SENSOR_WIDTH : integer := 12   -- ADC resolution
    );
    port (
        clk                : in  std_logic;
        reset              : in  std_logic;
        
        -- PWM control
        enable             : in  std_logic;
        duty_cycle         : in  std_logic_vector(PWM_WIDTH-1 downto 0);
        
        -- Sensor inputs
        current_value      : in  std_logic_vector(SENSOR_WIDTH-1 downto 0);
        voltage_value      : in  std_logic_vector(SENSOR_WIDTH-1 downto 0);
        temperature_value  : in  std_logic_vector(SENSOR_WIDTH-1 downto 0);
        
        -- Safety thresholds
        current_threshold  : in  std_logic_vector(SENSOR_WIDTH-1 downto 0);
        voltage_threshold  : in  std_logic_vector(SENSOR_WIDTH-1 downto 0);
        temp_threshold     : in  std_logic_vector(SENSOR_WIDTH-1 downto 0);
        hysteresis         : in  std_logic_vector(SENSOR_WIDTH-1 downto 0);
        
        -- Outputs
        pwm_out            : out std_logic;
        interlock_active   : out std_logic;
        fault_current      : out std_logic;
        fault_voltage      : out std_logic;
        fault_temperature  : out std_logic
    );
end entity pwm_controller;

architecture rtl of pwm_controller is
    -- Internal signals
    signal pwm_raw            : std_logic;  -- PWM before interlock
    signal interlock_active_i : std_logic;  -- Interlock status
    signal pwm_enable_safe    : std_logic;  -- Enable with safety check
    
begin
    -- Instantiate PWM generator
    pwm_gen: entity work.pwm_generator
        generic map (
            COUNTER_WIDTH => PWM_WIDTH
        )
        port map (
            clk        => clk,
            reset      => reset,
            enable     => pwm_enable_safe,  -- Use safe enable signal
            duty_cycle => duty_cycle,
            pwm_out    => pwm_raw
        );
    
    -- Instantiate interlock system
    interlock_sys: entity work.interlock
        generic map (
            SENSOR_WIDTH => SENSOR_WIDTH
        )
        port map (
            clk               => clk,
            reset             => reset,
            current_value     => current_value,
            voltage_value     => voltage_value,
            temperature_value => temperature_value,
            current_threshold => current_threshold,
            voltage_threshold => voltage_threshold,
            temp_threshold    => temp_threshold,
            hysteresis        => hysteresis,
            interlock_active  => interlock_active_i,
            fault_current     => fault_current,
            fault_voltage     => fault_voltage,
            fault_temperature => fault_temperature
        );
    
    -- Safety logic: PWM only enabled if no interlock AND user enables
    pwm_enable_safe <= enable and (not interlock_active_i);
    
    -- Final output with safety gate
    -- CRITICAL: This ensures PWM is ALWAYS disabled during fault
    pwm_out <= pwm_raw and (not interlock_active_i);
    
    -- Pass through interlock status
    interlock_active <= interlock_active_i;
    
end architecture rtl;

tb/pwm_controller_tb.vhdl
library ieee;
use ieee.std_logic_1164.all;
use ieee.numeric_std.all;

entity pwm_controller_tb is
end entity pwm_controller_tb;

architecture sim of pwm_controller_tb is
    constant CLK_PERIOD   : time := 10 ns;
    constant PWM_WIDTH    : integer := 8;
    constant SENSOR_WIDTH : integer := 12;
    
    signal clk                : std_logic := '0';
    signal reset              : std_logic := '0';
    signal enable             : std_logic := '0';
    signal duty_cycle         : std_logic_vector(PWM_WIDTH-1 downto 0);
    signal current_value      : std_logic_vector(SENSOR_WIDTH-1 downto 0);
    signal voltage_value      : std_logic_vector(SENSOR_WIDTH-1 downto 0);
    signal temperature_value  : std_logic_vector(SENSOR_WIDTH-1 downto 0);
    signal current_threshold  : std_logic_vector(SENSOR_WIDTH-1 downto 0);
    signal voltage_threshold  : std_logic_vector(SENSOR_WIDTH-1 downto 0);
    signal temp_threshold     : std_logic_vector(SENSOR_WIDTH-1 downto 0);
    signal hysteresis         : std_logic_vector(SENSOR_WIDTH-1 downto 0);
    signal pwm_out            : std_logic;
    signal interlock_active   : std_logic;
    signal fault_current      : std_logic;
    signal fault_voltage      : std_logic;
    signal fault_temperature  : std_logic;
    
    signal sim_done : boolean := false;
    
begin
    -- Instantiate complete PWM controller
    uut: entity work.pwm_controller
        generic map (
            PWM_WIDTH    => PWM_WIDTH,
            SENSOR_WIDTH => SENSOR_WIDTH
        )
        port map (
            clk               => clk,
            reset             => reset,
            enable            => enable,
            duty_cycle        => duty_cycle,
            current_value     => current_value,
            voltage_value     => voltage_value,
            temperature_value => temperature_value,
            current_threshold => current_threshold,
            voltage_threshold => voltage_threshold,
            temp_threshold    => temp_threshold,
            hysteresis        => hysteresis,
            pwm_out           => pwm_out,
            interlock_active  => interlock_active,
            fault_current     => fault_current,
            fault_voltage     => fault_voltage,
            fault_temperature => fault_temperature
        );
    
    -- Clock generation
    clk_gen: process
    begin
        while not sim_done loop
            clk <= '0';
            wait for CLK_PERIOD/2;
            clk <= '1';
            wait for CLK_PERIOD/2;
        end loop;
        wait;
    end process;
    
    -- Stimulus
    stim: process
    begin
        -- Initialize
        reset <= '1';
        enable <= '0';
        duty_cycle        <= std_logic_vector(to_unsigned(128, PWM_WIDTH)); -- 50% duty
        current_value     <= std_logic_vector(to_unsigned(2000, SENSOR_WIDTH));
        voltage_value     <= std_logic_vector(to_unsigned(2500, SENSOR_WIDTH));
        temperature_value <= std_logic_vector(to_unsigned(2000, SENSOR_WIDTH));
        
        -- Set safety thresholds
        current_threshold <= std_logic_vector(to_unsigned(3000, SENSOR_WIDTH));
        voltage_threshold <= std_logic_vector(to_unsigned(3500, SENSOR_WIDTH));
        temp_threshold    <= std_logic_vector(to_unsigned(2800, SENSOR_WIDTH));
        hysteresis        <= std_logic_vector(to_unsigned(200, SENSOR_WIDTH));
        
        wait for 50 ns;
        reset <= '0';
        wait for 50 ns;
        
        -- Test 1: Normal PWM operation (no faults)
        report "Test 1: Normal PWM operation";
        enable <= '1';
        wait for 3000 ns;  -- Let PWM run for multiple cycles
        
        -- Test 2: Overcurrent fault while PWM is running
        report "Test 2: Overcurrent fault - PWM should stop immediately";
        current_value <= std_logic_vector(to_unsigned(3200, SENSOR_WIDTH));
        wait for 2000 ns;  -- PWM should be disabled
        
        -- Test 3: Clear the fault
        report "Test 3: Clear fault - PWM should resume";
        current_value <= std_logic_vector(to_unsigned(2700, SENSOR_WIDTH));
        wait for 2000 ns;  -- PWM should resume
        
        -- Test 4: Change duty cycle during operation
        report "Test 4: Change duty cycle to 25%";
        duty_cycle <= std_logic_vector(to_unsigned(64, PWM_WIDTH)); -- 25%
        wait for 2000 ns;
        
        -- Test 5: Overvoltage fault
        report "Test 5: Overvoltage fault";
        voltage_value <= std_logic_vector(to_unsigned(3700, SENSOR_WIDTH));
        wait for 1500 ns;
        
        -- Test 6: Multiple simultaneous faults
        report "Test 6: Multiple simultaneous faults";
        current_value     <= std_logic_vector(to_unsigned(3300, SENSOR_WIDTH));
        temperature_value <= std_logic_vector(to_unsigned(2900, SENSOR_WIDTH));
        wait for 1500 ns;
        
        -- Test 7: Clear all faults
        report "Test 7: Clear all faults - resume operation";
        current_value     <= std_logic_vector(to_unsigned(2000, SENSOR_WIDTH));
        voltage_value     <= std_logic_vector(to_unsigned(2500, SENSOR_WIDTH));
        temperature_value <= std_logic_vector(to_unsigned(2000, SENSOR_WIDTH));
        wait for 2000 ns;
        
        -- Test 8: Change to 75% duty cycle
        report "Test 8: Change to 75% duty cycle";
        duty_cycle <= std_logic_vector(to_unsigned(192, PWM_WIDTH)); -- 75%
        wait for 2000 ns;
        
        -- Test 9: Disable PWM manually
        report "Test 9: Disable PWM manually";
        enable <= '0';
        wait for 1000 ns;
        
        -- Test 10: Re-enable
        report "Test 10: Re-enable PWM";
        enable <= '1';
        wait for 2000 ns;
        
        -- End simulation
        report "Simulation complete";
        sim_done <= true;
        wait;
    end process;
    
end architecture sim;

sim/pwm_controller.vcd
$date
  Thu Jan 29 13:39:59 2026
$end
$version
  GHDL v0
$end
$timescale
  1 fs
$end
$scope module standard $end
$upscope $end
$scope module std_logic_1164 $end
$upscope $end
$scope module numeric_std $end
$upscope $end
$scope module pwm_controller_tb $end
$var reg 1 ! clk $end
$var reg 1 " reset $end
$var reg 1 # enable $end
$var reg 8 $ duty_cycle[7:0] $end
$var reg 12 % current_value[11:0] $end
$var reg 12 & voltage_value[11:0] $end
$var reg 12 ' temperature_value[11:0] $end
$var reg 12 ( current_threshold[11:0] $end
$var reg 12 ) voltage_threshold[11:0] $end
$var reg 12 * temp_threshold[11:0] $end
$var reg 12 + hysteresis[11:0] $end
$var reg 1 , pwm_out $end
$var reg 1 - interlock_active $end
$var reg 1 . fault_current $end
$var reg 1 / fault_voltage $end
$var reg 1 0 fault_temperature $end
$var reg 1 1 sim_done $end
$scope module uut $end
$var reg 1 2 clk $end
$var reg 1 3 reset $end
$var reg 1 4 enable $end
$var reg 8 5 duty_cycle[7:0] $end
$var reg 12 6 current_value[11:0] $end
$var reg 12 7 voltage_value[11:0] $end
$var reg 12 8 temperature_value[11:0] $end
$var reg 12 9 current_threshold[11:0] $end
$var reg 12 : voltage_threshold[11:0] $end
$var reg 12 ; temp_threshold[11:0] $end
$var reg 12 < hysteresis[11:0] $end
$var reg 1 = pwm_out $end
$var reg 1 > interlock_active $end
$var reg 1 ? fault_current $end
$var reg 1 @ fault_voltage $end
$var reg 1 A fault_temperature $end
$var reg 1 B pwm_raw $end
$var reg 1 C interlock_active_i $end
$var reg 1 D pwm_enable_safe $end
$scope module pwm_gen $end
$var reg 1 E clk $end
$var reg 1 F reset $end
$var reg 1 G enable $end
$var reg 8 H duty_cycle[7:0] $end
$var reg 1 I pwm_out $end
$var reg 8 J counter[7:0] $end
$var reg 8 K duty_unsigned[7:0] $end
$upscope $end
$scope module interlock_sys $end
$var reg 1 L clk $end
$var reg 1 M reset $end
$var reg 12 N current_value[11:0] $end
$var reg 12 O voltage_value[11:0] $end
$var reg 12 P temperature_value[11:0] $end
$var reg 12 Q current_threshold[11:0] $end
$var reg 12 R voltage_threshold[11:0] $end
$var reg 12 S temp_threshold[11:0] $end
$var reg 12 T hysteresis[11:0] $end
$var reg 1 U interlock_active $end
$var reg 1 V fault_current $end
$var reg 1 W fault_voltage $end
$var reg 1 X fault_temperature $end
$var reg 12 Y current_u[11:0] $end
$var reg 12 Z voltage_u[11:0] $end
$var reg 12 [ temperature_u[11:0] $end
$var reg 12 \ current_thresh_u[11:0] $end
$var reg 12 ] voltage_thresh_u[11:0] $end
$var reg 12 ^ temp_thresh_u[11:0] $end
$var reg 12 _ hysteresis_u[11:0] $end
$var reg 1 ` fault_current_int $end
$var reg 1 a fault_voltage_int $end
$var reg 1 b fault_temperature_int $end
$upscope $end
$upscope $end
$upscope $end
$enddefinitions $end
#0
0!
1"
0#
b10000000 $
b011111010000 %
b100111000100 &
b011111010000 '
b101110111000 (
b110110101100 )
b101011110000 *
b000011001000 +
0,
0-
0.
0/
00
01
02
13
04
b10000000 5
b011111010000 6
b100111000100 7
b011111010000 8
b101110111000 9
b110110101100 :
b101011110000 ;
b000011001000 <
0=
0>
0?
0@
0A
0B
0C
0D
0E
1F
0G
b10000000 H
0I
b00000000 J
b10000000 K
0L
1M
b011111010000 N
b100111000100 O
b011111010000 P
b101110111000 Q
b110110101100 R
b101011110000 S
b000011001000 T
0U
0V
0W
0X
b011111010000 Y
b100111000100 Z
b011111010000 [
b101110111000 \
b110110101100 ]
b101011110000 ^
b000011001000 _
0`
0a
0b
#5000000
1!
12
1E
1L
#10000000
0!
02
0E
0L
#15000000
1!
12
1E
1L
#20000000
0!
02
0E
0L
#25000000
1!
12
1E
1L
#30000000
0!
02
0E
0L
#35000000
1!
12
1E
1L
#40000000
0!
02
0E
0L
#45000000
1!
12
1E
1L
#50000000
0!
0"
02
03
0E
0F
0L
0M
#55000000
1!
12
1E
1L
#60000000
0!
02
0E
0L
#65000000
1!
12
1E
1L
#70000000
0!
02
0E
0L
#75000000
1!
12
1E
1L
#80000000
0!
02
0E
0L
#85000000
1!
12
1E
1L
#90000000
0!
02
0E
0L
#95000000
1!
12
1E
1L
#100000000
0!
1#
02
14
1D
0E
1G
0L
#105000000
1!
1,
12
1=
1B
1E
1I
b00000001 J
1L
#110000000
0!
02
0E
0L
#115000000
1!
12
1E
b00000010 J
1L
#120000000
0!
02
0E
0L
#125000000
1!
12
1E
b00000011 J
1L
#130000000
0!
02
0E
0L
#135000000
1!
12
1E
b00000100 J
1L
#140000000
0!
02
0E
0L
#145000000
1!
12
1E
b00000101 J
1L
#150000000
0!
02
0E
0L
#155000000
1!
12
1E
b00000110 J
1L
#160000000
0!
02
0E
0L
#165000000
1!
12
1E
b00000111 J
1L
#170000000
0!
02
0E
0L
#175000000
1!
12
1E
b00001000 J
1L
#180000000
0!
02
0E
0L
#185000000
1!
12
1E
b00001001 J
1L
#190000000
0!
02
0E
0L
#195000000
1!
12
1E
b00001010 J
1L
#200000000
0!
02
0E
0L
#205000000
1!
12
1E
b00001011 J
1L
#210000000
0!
02
0E
0L
#215000000
1!
12
1E
b00001100 J
1L
#220000000
0!
02
0E
0L
#225000000
1!
12
1E
b00001101 J
1L
#230000000
0!
02
0E
0L
#235000000
1!
12
1E
b00001110 J
1L
#240000000
0!
02
0E
0L
#245000000
1!
12
1E
b00001111 J
1L
#250000000
0!
02
0E
0L
#255000000
1!
12
1E
b00010000 J
1L
#260000000
0!
02
0E
0L
#265000000
1!
12
1E
b00010001 J
1L
#270000000
0!
02
0E
0L
#275000000
1!
12
1E
b00010010 J
1L
#280000000
0!
02
0E
0L
#285000000
1!
12
1E
b00010011 J
1L
#290000000
0!
02
0E
0L
#295000000
1!
12
1E
b00010100 J
1L
#300000000
0!
02
0E
0L
#305000000
1!
12
1E
b00010101 J
1L
#310000000
0!
02
0E
0L
#315000000
1!
12
1E
b00010110 J
1L
#320000000
0!
02
0E
0L
#325000000
1!
12
1E
b00010111 J
1L
#330000000
0!
02
0E
0L
#335000000
1!
12
1E
b00011000 J
1L
#340000000
0!
02
0E
0L
#345000000
1!
12
1E
b00011001 J
1L
#350000000
0!
02
0E
0L
#355000000
1!
12
1E
b00011010 J
1L
#360000000
0!
02
0E
0L
#365000000
1!
12
1E
b00011011 J
1L
#370000000
0!
02
0E
0L
#375000000
1!
12
1E
b00011100 J
1L
#380000000
0!
02
0E
0L
#385000000
1!
12
1E
b00011101 J
1L
#390000000
0!
02
0E
0L
#395000000
1!
12
1E
b00011110 J
1L
#400000000
0!
02
0E
0L
#405000000
1!
12
1E
b00011111 J
1L
#410000000
0!
02
0E
0L
#415000000
1!
12
1E
b00100000 J
1L
#420000000
0!
02
0E
0L
#425000000
1!
12
1E
b00100001 J
1L
#430000000
0!
02
0E
0L
#435000000
1!
12
1E
b00100010 J
1L
#440000000
0!
02
0E
0L
#445000000
1!
12
1E
b00100011 J
1L
#450000000
0!
02
0E
0L
#455000000
1!
12
1E
b00100100 J
1L
#460000000
0!
02
0E
0L
#465000000
1!
12
1E
b00100101 J
1L
#470000000
0!
02
0E
0L
#475000000
1!
12
1E
b00100110 J
1L
#480000000
0!
02
0E
0L
#485000000
1!
12
1E
b00100111 J
1L
#490000000
0!
02
0E
0L
#495000000
1!
12
1E
b00101000 J
1L
#500000000
0!
02
0E
0L
#505000000
1!
12
1E
b00101001 J
1L
#510000000
0!
02
0E
0L
#515000000
1!
12
1E
b00101010 J
1L
#520000000
0!
02
0E
0L
#525000000
1!
12
1E
b00101011 J
1L
#530000000
0!
02
0E
0L
#535000000
1!
12
1E
b00101100 J
1L
#540000000
0!
02
0E
0L
#545000000
1!
12
1E
b00101101 J
1L
#550000000
0!
02
0E
0L
#555000000
1!
12
1E
b00101110 J
1L
#560000000
0!
02
0E
0L
#565000000
1!
12
1E
b00101111 J
1L
#570000000
0!
02
0E
0L
#575000000
1!
12
1E
b00110000 J
1L
#580000000
0!
02
0E
0L
#585000000
1!
12
1E
b00110001 J
1L
#590000000
0!
02
0E
0L
#595000000
1!
12
1E
b00110010 J
1L
#600000000
0!
02
0E
0L
#605000000
1!
12
1E
b00110011 J
1L
#610000000
0!
02
0E
0L
#615000000
1!
12
1E
b00110100 J
1L
#620000000
0!
02
0E
0L
#625000000
1!
12
1E
b00110101 J
1L
#630000000
0!
02
0E
0L
#635000000
1!
12
1E
b00110110 J
1L
#640000000
0!
02
0E
0L
#645000000
1!
12
1E
b00110111 J
1L
#650000000
0!
02
0E
0L
#655000000
1!
12
1E
b00111000 J
1L
#660000000
0!
02
0E
0L
#665000000
1!
12
1E
b00111001 J
1L
#670000000
0!
02
0E
0L
#675000000
1!
12
1E
b00111010 J
1L
#680000000
0!
02
0E
0L
#685000000
1!
12
1E
b00111011 J
1L
#690000000
0!
02
0E
0L
#695000000
1!
12
1E
b00111100 J
1L
#700000000
0!
02
0E
0L
#705000000
1!
12
1E
b00111101 J
1L
#710000000
0!
02
0E
0L
#715000000
1!
12
1E
b00111110 J
1L
#720000000
0!
02
0E
0L
#725000000
1!
12
1E
b00111111 J
1L
#730000000
0!
02
0E
0L
#735000000
1!
12
1E
b01000000 J
1L
#740000000
0!
02
0E
0L
#745000000
1!
12
1E
b01000001 J
1L
#750000000
0!
02
0E
0L
#755000000
1!
12
1E
b01000010 J
1L
#760000000
0!
02
0E
0L
#765000000
1!
12
1E
b01000011 J
1L
#770000000
0!
02
0E
0L
#775000000
1!
12
1E
b01000100 J
1L
#780000000
0!
02
0E
0L
#785000000
1!
12
1E
b01000101 J
1L
#790000000
0!
02
0E
0L
#795000000
1!
12
1E
b01000110 J
1L
#800000000
0!
02
0E
0L
#805000000
1!
12
1E
b01000111 J
1L
#810000000
0!
02
0E
0L
#815000000
1!
12
1E
b01001000 J
1L
#820000000
0!
02
0E
0L
#825000000
1!
12
1E
b01001001 J
1L
#830000000
0!
02
0E
0L
#835000000
1!
12
1E
b01001010 J
1L
#840000000
0!
02
0E
0L
#845000000
1!
12
1E
b01001011 J
1L
#850000000
0!
02
0E
0L
#855000000
1!
12
1E
b01001100 J
1L
#860000000
0!
02
0E
0L
#865000000
1!
12
1E
b01001101 J
1L
#870000000
0!
02
0E
0L
#875000000
1!
12
1E
b01001110 J
1L
#880000000
0!
02
0E
0L
#885000000
1!
12
1E
b01001111 J
1L
#890000000
0!
02
0E
0L
#895000000
1!
12
1E
b01010000 J
1L
#900000000
0!
02
0E
0L
#905000000
1!
12
1E
b01010001 J
1L
#910000000
0!
02
0E
0L
#915000000
1!
12
1E
b01010010 J
1L
#920000000
0!
02
0E
0L
#925000000
1!
12
1E
b01010011 J
1L
#930000000
0!
02
0E
0L
#935000000
1!
12
1E
b01010100 J
1L
#940000000
0!
02
0E
0L
#945000000
1!
12
1E
b01010101 J
1L
#950000000
0!
02
0E
0L
#955000000
1!
12
1E
b01010110 J
1L
#960000000
0!
02
0E
0L
#965000000
1!
12
1E
b01010111 J
1L
#970000000
0!
02
0E
0L
#975000000
1!
12
1E
b01011000 J
1L
#980000000
0!
02
0E
0L
#985000000
1!
12
1E
b01011001 J
1L
#990000000
0!
02
0E
0L
#995000000
1!
12
1E
b01011010 J
1L
#1000000000
0!
02
0E
0L
#1005000000
1!
12
1E
b01011011 J
1L
#1010000000
0!
02
0E
0L
#1015000000
1!
12
1E
b01011100 J
1L
#1020000000
0!
02
0E
0L
#1025000000
1!
12
1E
b01011101 J
1L
#1030000000
0!
02
0E
0L
#1035000000
1!
12
1E
b01011110 J
1L
#1040000000
0!
02
0E
0L
#1045000000
1!
12
1E
b01011111 J
1L
#1050000000
0!
02
0E
0L
#1055000000
1!
12
1E
b01100000 J
1L
#1060000000
0!
02
0E
0L
#1065000000
1!
12
1E
b01100001 J
1L
#1070000000
0!
02
0E
0L
#1075000000
1!
12
1E
b01100010 J
1L
#1080000000
0!
02
0E
0L
#1085000000
1!
12
1E
b01100011 J
1L
#1090000000
0!
02
0E
0L
#1095000000
1!
12
1E
b01100100 J
1L
#1100000000
0!
02
0E
0L
#1105000000
1!
12
1E
b01100101 J
1L
#1110000000
0!
02
0E
0L
#1115000000
1!
12
1E
b01100110 J
1L
#1120000000
0!
02
0E
0L
#1125000000
1!
12
1E
b01100111 J
1L
#1130000000
0!
02
0E
0L
#1135000000
1!
12
1E
b01101000 J
1L
#1140000000
0!
02
0E
0L
#1145000000
1!
12
1E
b01101001 J
1L
#1150000000
0!
02
0E
0L
#1155000000
1!
12
1E
b01101010 J
1L
#1160000000
0!
02
0E
0L
#1165000000
1!
12
1E
b01101011 J
1L
#1170000000
0!
02
0E
0L
#1175000000
1!
12
1E
b01101100 J
1L
#1180000000
0!
02
0E
0L
#1185000000
1!
12
1E
b01101101 J
1L
#1190000000
0!
02
0E
0L
#1195000000
1!
12
1E
b01101110 J
1L
#1200000000
0!
02
0E
0L
#1205000000
1!
12
1E
b01101111 J
1L
#1210000000
0!
02
0E
0L
#1215000000
1!
12
1E
b01110000 J
1L
#1220000000
0!
02
0E
0L
#1225000000
1!
12
1E
b01110001 J
1L
#1230000000
0!
02
0E
0L
#1235000000
1!
12
1E
b01110010 J
1L
#1240000000
0!
02
0E
0L
#1245000000
1!
12
1E
b01110011 J
1L
#1250000000
0!
02
0E
0L
#1255000000
1!
12
1E
b01110100 J
1L
#1260000000
0!
02
0E
0L
#1265000000
1!
12
1E
b01110101 J
1L
#1270000000
0!
02
0E
0L
#1275000000
1!
12
1E
b01110110 J
1L
#1280000000
0!
02
0E
0L
#1285000000
1!
12
1E
b01110111 J
1L
#1290000000
0!
02
0E
0L
#1295000000
1!
12
1E
b01111000 J
1L
#1300000000
0!
02
0E
0L
#1305000000
1!
12
1E
b01111001 J
1L
#1310000000
0!
02
0E
0L
#1315000000
1!
12
1E
b01111010 J
1L
#1320000000
0!
02
0E
0L
#1325000000
1!
12
1E
b01111011 J
1L
#1330000000
0!
02
0E
0L
#1335000000
1!
12
1E
b01111100 J
1L
#1340000000
0!
02
0E
0L
#1345000000
1!
12
1E
b01111101 J
1L
#1350000000
0!
02
0E
0L
#1355000000
1!
12
1E
b01111110 J
1L
#1360000000
0!
02
0E
0L
#1365000000
1!
12
1E
b01111111 J
1L
#1370000000
0!
02
0E
0L
#1375000000
1!
12
1E
b10000000 J
1L
#1380000000
0!
02
0E
0L
#1385000000
1!
0,
12
0=
0B
1E
0I
b10000001 J
1L
#1390000000
0!
02
0E
0L
#1395000000
1!
12
1E
b10000010 J
1L
#1400000000
0!
02
0E
0L
#1405000000
1!
12
1E
b10000011 J
1L
#1410000000
0!
02
0E
0L
#1415000000
1!
12
1E
b10000100 J
1L
#1420000000
0!
02
0E
0L
#1425000000
1!
12
1E
b10000101 J
1L
#1430000000
0!
02
0E
0L
#1435000000
1!
12
1E
b10000110 J
1L
#1440000000
0!
02
0E
0L
#1445000000
1!
12
1E
b10000111 J
1L
#1450000000
0!
02
0E
0L
#1455000000
1!
12
1E
b10001000 J
1L
#1460000000
0!
02
0E
0L
#1465000000
1!
12
1E
b10001001 J
1L
#1470000000
0!
02
0E
0L
#1475000000
1!
12
1E
b10001010 J
1L
#1480000000
0!
02
0E
0L
#1485000000
1!
12
1E
b10001011 J
1L
#1490000000
0!
02
0E
0L
#1495000000
1!
12
1E
b10001100 J
1L
#1500000000
0!
02
0E
0L
#1505000000
1!
12
1E
b10001101 J
1L
#1510000000
0!
02
0E
0L
#1515000000
1!
12
1E
b10001110 J
1L
#1520000000
0!
02
0E
0L
#1525000000
1!
12
1E
b10001111 J
1L
#1530000000
0!
02
0E
0L
#1535000000
1!
12
1E
b10010000 J
1L
#1540000000
0!
02
0E
0L
#1545000000
1!
12
1E
b10010001 J
1L
#1550000000
0!
02
0E
0L
#1555000000
1!
12
1E
b10010010 J
1L
#1560000000
0!
02
0E
0L
#1565000000
1!
12
1E
b10010011 J
1L
#1570000000
0!
02
0E
0L
#1575000000
1!
12
1E
b10010100 J
1L
#1580000000
0!
02
0E
0L
#1585000000
1!
12
1E
b10010101 J
1L
#1590000000
0!
02
0E
0L
#1595000000
1!
12
1E
b10010110 J
1L
#1600000000
0!
02
0E
0L
#1605000000
1!
12
1E
b10010111 J
1L
#1610000000
0!
02
0E
0L
#1615000000
1!
12
1E
b10011000 J
1L
#1620000000
0!
02
0E
0L
#1625000000
1!
12
1E
b10011001 J
1L
#1630000000
0!
02
0E
0L
#1635000000
1!
12
1E
b10011010 J
1L
#1640000000
0!
02
0E
0L
#1645000000
1!
12
1E
b10011011 J
1L
#1650000000
0!
02
0E
0L
#1655000000
1!
12
1E
b10011100 J
1L
#1660000000
0!
02
0E
0L
#1665000000
1!
12
1E
b10011101 J
1L
#1670000000
0!
02
0E
0L
#1675000000
1!
12
1E
b10011110 J
1L
#1680000000
0!
02
0E
0L
#1685000000
1!
12
1E
b10011111 J
1L
#1690000000
0!
02
0E
0L
#1695000000
1!
12
1E
b10100000 J
1L
#1700000000
0!
02
0E
0L
#1705000000
1!
12
1E
b10100001 J
1L
#1710000000
0!
02
0E
0L
#1715000000
1!
12
1E
b10100010 J
1L
#1720000000
0!
02
0E
0L
#1725000000
1!
12
1E
b10100011 J
1L
#1730000000
0!
02
0E
0L
#1735000000
1!
12
1E
b10100100 J
1L
#1740000000
0!
02
0E
0L
